Workbook
Name JB_A: 'J Book Items Cons.'!$A$5:$A$3381
Name JB_B: 'J Book Items Cons.'!$E$5:$E$3381
Name JB_F: 'J Book Items Cons.'!$F$5:$F$3381
Name JB_S: 'J Book Items Cons.'!$V$5:$V$3381
Name JB_U: 'J Book Items Cons.'!$X$5:$X$3381
Name JB_V: 'J Book Items Cons.'!$Y$5:$Y$3381
Name JB_W: 'J Book Items Cons.'!$Z$5:$Z$3381
Name JB_R: 'J Book Items Cons.'!$R$5:$R$3381
Name JB_N: 'J Book Items Cons.'!$N$5:$N$3381
Name JB_L: 'J Book Items Cons.'!$L$5:$L$3381
Name JB_27U: 'J Book Items Cons.'!$U$5:$U$3381
Name JB_27S: 'J Book Items Cons.'!$S$5:$S$3381

Sheet J Book Items Cons.
A1: J Book Items Consolidated
A2: Consolidated line-item budget data from SCN, OPN, OMN, NWCF, and USCG justification books
A4: Source Book | B4: Color of Money | C4: Line Item Number | D4: Line Item Title | E4: Bucket | F4: Bucket Sub Category | G4: Description | H4: Prior Years ($K) | I4: FY2024 ($K) | J4: FY2025 ($K) | K4: FY2025 Required ($K) | L4: FY2026 Request ($K) | M4: FY2026 Reconciliation ($K) | N4: FY2026 Total ($K) | O4: FY2026 Required ($K) | P4: FY2026 DAA Mandatory ($K) | Q4: FY2026 DAA Final Bill ($K) | R4: FY2026 DAA Enacted Total ($K) | S4: FY2027 Request ($K) | T4: FY2027 Mandatory Request ($K) | U4: FY2027 Total ($K) | V4: Row Type | W4: Parent Item | X4: Vessel Service | Y4: Vessel Category | Z4: Vessel Type | AA4: Vessel Hull | AB4: Citation | AC4: Source Page | AF4: Program Element Number | AG4: Project | AH4: Cost Element | AI4: Market | AJ4: Submarket | AK4: PE Description
A5: SCN | B5: Procurement | C5: 1045 | D5: COLUMBIA Class Submarine | E5: 1 | F5: Full ship DD&C | G5: MISSION: Strategic Deterrence. The COLUMBIA Class Program is an Acquisition Category (ACAT) ID Major Defense Acquisition Program (MDAP) to design, construct, and deliver a replacement for the OHIO Class Fleet Ballistic Missile Submarines (SSBNs), which begins retiring at a rate of one per year | I5: 0 | J5: 3364835 | L5: 3928828 | M5: 0 | N5: 3928828 | Q5: 3928828 | R5: 3928828 | S5: 10233832 | U5: 10233832 | V5: [PARENT] | X5: USN | Y5: Combatant Ships | Z5: Submarines | AA5: SSBN | AB5: P-40 Exhibit > LI 1045 > COLUMBIA Class Submarine | AC5: 31 | AF5: 1045 | AI5: Maritime Platforms & Systems | AJ5: Submarines - SSBN/SSGN | AK5: MISSION: Strategic Deterrence. The COLUMBIA Class Program is an Acquisition Category (ACAT) ID Major Defense Acquisition Program (MDAP) to design, construct, and deliver a replacement for the OHIO Class Fleet Ballistic Missile Submarines (SSBNs), which begins retiring at a rate of one per year beginning in 2027. The mission of the COLUMBIA SSBN is to maintain an appropriate state of readiness to assist in deterring nuclear attack on the United States and its allies. In the event deterrence should fail, the force must be capable of launching missiles against pre-planned or adaptively planned targets. To fulfill this mission COLUMBIA SSBNs must be capable of performing extended strategic deterrent patrols without requiring assistance or replenishment. It does not have a requirement for additional capabilities or other missions unrelated to survivable strategic nuclear deterrence. Armament: Torpedo Tubes Ballistic Missile Tubes Major Electronics: Trident D5 Strategic Weapons System Command, Control, Communications and Intelligence System - Open System Architecture - Twenty-three Subsystems Note: The FY 2026 request for COLUMBIA Class Submarine includes $8,994,594 thousand of discretionary funding and $1,925,892 thousand of mandatory (reconciliation) funding for a total of $10,920,486 thousand. While the total FY 2026 discretionary funding decreased by $1,426,814 million when compared to the FY 2026 funding in the FY 2025 submission ($10,421,408 thousand), the overall funding (mandatory plus discretionary) for COLUMBIA Class Submarine increased by $499,078 thousand when compared to the FY 2026 funding in the FY 2025 submission. FY2026 is the first year of incremental full funding for the third ship, SSBN 828. Additionally, FY2026 funds the COLUMBIA Class Program to the NAVSEA 05C's 2023 cost estimate and preliminary Build II (SSBN 828-832) contract negotiations. The FY2026 budget and P5 breakout also includes Cost to Complete for Build I (SSBN 826-827), however, funding is reflected in FY2027-2030. The budget also includes continuing Integrated Enterprise Plan (IEP) funding initiatives, material procurement for future ships, and funding for the Maritime Industrial Base (MIB) (previously referred to as the Submarine Industrial Base/SIB). These MIB investments provide enterprise funding to strengthen the MIB to support a generational increase in submarine demand and includes supplier development, shipbuilder/supplier infrastructure, workforce development, technology opportunities, and strategic outsourcing. Investments are targeted to support uplift of the MIB to achieve a "1+2 " Production Cadence, strengthening the MIB and reprioritizing/growing infrastructure to support new construction goals and increased demand as well as improved maintenance and sustainment for the submarine fleet. The MIB funding profile reflects the funding provided by the Indo-Pacific Supplemental Appropriations Act, 2024 ($1,955M) to support improvements to the MIB. FY2025 Plans includes supplier development Congressional adds +$5M for explosion welding facilities and +$18.5M for tube/propulsor facilitization. In August 2020, the COLUMBIA Class program completed its Construction Authorization In Progress Review (IPR). The Milestone Decision Authority (MDA) approved the program for entry into Build I construction on 28 August 2020, pending FY2021 congressional authorization and appropriation. As a result of the IPR, the FY2022 budget submission reflected SSBN 826-837 requirements aligned to the NAVSEA 05C's 2020 cost estimate plus additional funding for SSBN 826 based on the CAPE Lead Ship Assessment (LSA) cost estimate (+$155M FY2022-FY2023). At the COLUMBIA Program Semi-Annual IPR held on August 30, 2021, the MDA directed COLUMBIA to be funded to the program baseline, including IEP funding. FY2026 reflects funding to the NAVSEA 05C's 2023 cost estimate (including impacts from inflation) as well as to the results of preliminary Build II contract negotiations for basic construction costs. The Build II preliminary negotiations accounts for anticipated cost growth based on current vendor proposals, current shipbuilder performance, and inflation. The Program is completing an updated cost estimate and CAPE Independent Cost Estimate (ICE) to support Build II contract negotiation and award. The IEP funding leverages Congressional authorities and is aligned to OSD and Navy direction to execute COLUMBIA Class schedules needed to accelerate ship delivery schedules to reduce the strategic deterrence coverage gaps during transition from OHIO SSBNs to CLB SSBNs and the transition from D5LE to D5LE2 missiles. It is crucial to maintain force structure necessary to meet USSTRATCOM requirements for Sea-Based Strategic Deterrence (SBSD). Total MIB funding of $1,352M in FY2026 is accounted for in SSBN 837 Plans Costs P-5c Cost Category to ensure it is visible and can be appropriately tracked and managed. Since the FY2025 submission, FY2026 was reduced by $50M and rephased later into the FYDP FY2021 was the year of authorization for the lead ship, DISTRICT OF COLUMBIA (SSBN 826), and was a new start program due to FY2021 being the first year of incremental full funding. FY2022 and FY2023 were the second and third year of full funding for lead ship, DISTRICT OF COLUMBIA. FY2024 was the year of authorization for the second ship, WISCONSIN (SSBN 827), and first year of incremental funding for the second ship; FY2025 is the second year of incremental funding. FY2026 will be the year of authorization and the first year of incremental funding for the third ship. The budget request supports continued detailed design and construction of CFE and GFE systems to build, test, outfit, and deliver SSBN 828 and later ships. Funding also supports Continuous Production of Missile Tubes, Advance Construction (AC), EOQ for Multi-Program Procurement, Continuous Production of Shipyard Manufactured Items, and Supplier Development to reduce COLUMBIA Class construction schedule risk executed in accordance with enhanced acquisition authorities contained within the National Sea-Based Deterrence Fund (NSBDF), 10 U.S.C. 2218a. The Navy executed a Build I contract for the first two COLUMBIA class submarines (SSBN 826 and SSBN 827), detailed below. The Navy's FY2026 budget was altered to reflect three-year incremental funding profile for all COLUMBIA (CLB) Build II Ships and continues for rest of class. This results in a reduction of $3.1B in FY2026 (shifted into follow years). This incremental full funding profile supports the phased requirements to meet the objective SSBN 828 delivery date. A Contract Modification for ongoing design/advance construction efforts was awarded on 22 June 2020, which also included the Build I Option for the First Two Ships. This was a Pre-Priced Option for the two ships, SSBN 826 and SSBN 827, and associated design/support efforts. This was a modification of the current IPPD contract (N00024-17-C-2117) and is in line with the program's approved Acquisition Strategy. The program received authorization for SSBN 826 in FY2021, funded with three years of incremental funding in FY2021-2023, and SSBN 827 was authorized in FY2024, funded with two years of incremental funding in FY2024-2025. In December 2022, program awarded an additional pre-priced contract modification of IPPD to support Build II/III Advance Procurement / Advance Construction, EOQ for Build II, and MIB efforts. CLB and VIRGINIA Class (VCS) Programs are executing an innovative contracting approach (similar to CLB Build I) which will coordinate CLB Build II with VCS new construction contracting efforts (VCS FY2024 ships and Block VI (FY2025-2029)) to maximize efficiency and stability across the industrial base. The coordination of three separate contract actions eliminates redundant effort by negotiating multiple contracts simultaneously while allowing the shipbuilders to place material orders for multiple ships in concert with VCS which improves stability for supplier base to de-risk schedules. Since the FY2025 submission, the COLUMBIA Class Program continues investment in initiatives to reduce construction schedule risk and enable cost savings (Multi-Program Material Procurement (MPMP), Continuous Production (CP) of Missile Tubes/Outfitting, Ordnance Systems and Shipyard Manufactured Components, Economic Order Quantity efforts, and Advance Construction). Increased investment in Strategic Weapons System (SWS) Shipboard Systems EOQ and Continuous Production leverages additional opportunities to mitigate obsolescence and construction schedule risks and realize additional cost savings outside of the FYDP. The Navy in FY2026 continues to fund additional IEP initiatives (EOQ/MPMP, CP, Missile Tube Outfitting, AC/AP, and Production Backup Units) which is crucial to de-risk and execute IEP Objective schedules. Total class cost savings is $2,010M. Details are contained in the P-10. The first Missile Tube Module (MTM) is funded through RDTEN Program Element 0603595N for $584M; additional $195M funds added due to MTM performance growth in the FY2026 submission.
A6: SCN | B6: Procurement | D6: COLUMBIA Class Submarine - SFF for FY 2024 | E6: 1 | F6: Full ship DD&C | J6: 3364835 | V6: [SUB] | W6: 1045 / COLUMBIA Class Submarine | X6: USN | Y6: Combatant Ships | Z6: Submarines | AA6: SSBN | AB6: P-1 Exhibit > BA 01 > Line 1 SFF | AC6: 12 | AF6: 1045 | AI6: Maritime Platforms & Systems | AJ6: Submarines - SSBN/SSGN | AK6: MISSION: Strategic Deterrence. The COLUMBIA Class Program is an Acquisition Category (ACAT) ID Major Defense Acquisition Program (MDAP) to design, construct, and deliver a replacement for the OHIO Class Fleet Ballistic Missile Submarines (SSBNs), which begins retiring at a rate of one per year beginning in 2027. The mission of the COLUMBIA SSBN is to maintain an appropriate state of readiness to assist in deterring nuclear attack on the United States and its allies. In the event deterrence should fail, the force must be capable of launching missiles against pre-planned or adaptively planned targets. To fulfill this mission COLUMBIA SSBNs must be capable of performing extended strategic deterrent patrols without requiring assistance or replenishment. It does not have a requirement for additional capabilities or other missions unrelated to survivable strategic nuclear deterrence. Armament: Torpedo Tubes Ballistic Missile Tubes Major Electronics: Trident D5 Strategic Weapons System Command, Control, Communications and Intelligence System - Open System Architecture - Twenty-three Subsystems Note: The FY 2026 request for COLUMBIA Class Submarine includes $8,994,594 thousand of discretionary funding and $1,925,892 thousand of mandatory (reconciliation) funding for a total of $10,920,486 thousand. While the total FY 2026 discretionary funding decreased by $1,426,814 million when compared to the FY 2026 funding in the FY 2025 submission ($10,421,408 thousand), the overall funding (mandatory plus discretionary) for COLUMBIA Class Submarine increased by $499,078 thousand when compared to the FY 2026 funding in the FY 2025 submission. FY2026 is the first year of incremental full funding for the third ship, SSBN 828. Additionally, FY2026 funds the COLUMBIA Class Program to the NAVSEA 05C's 2023 cost estimate and preliminary Build II (SSBN 828-832) contract negotiations. The FY2026 budget and P5 breakout also includes Cost to Complete for Build I (SSBN 826-827), however, funding is reflected in FY2027-2030. The budget also includes continuing Integrated Enterprise Plan (IEP) funding initiatives, material procurement for future ships, and funding for the Maritime Industrial Base (MIB) (previously referred to as the Submarine Industrial Base/SIB). These MIB investments provide enterprise funding to strengthen the MIB to support a generational increase in submarine demand and includes supplier development, shipbuilder/supplier infrastructure, workforce development, technology opportunities, and strategic outsourcing. Investments are targeted to support uplift of the MIB to achieve a "1+2 " Production Cadence, strengthening the MIB and reprioritizing/growing infrastructure to support new construction goals and increased demand as well as improved maintenance and sustainment for the submarine fleet. The MIB funding profile reflects the funding provided by the Indo-Pacific Supplemental Appropriations Act, 2024 ($1,955M) to support improvements to the MIB. FY2025 Plans includes supplier development Congressional adds +$5M for explosion welding facilities and +$18.5M for tube/propulsor facilitization. In August 2020, the COLUMBIA Class program completed its Construction Authorization In Progress Review (IPR). The Milestone Decision Authority (MDA) approved the program for entry into Build I construction on 28 August 2020, pending FY2021 congressional authorization and appropriation. As a result of the IPR, the FY2022 budget submission reflected SSBN 826-837 requirements aligned to the NAVSEA 05C's 2020 cost estimate plus additional funding for SSBN 826 based on the CAPE Lead Ship Assessment (LSA) cost estimate (+$155M FY2022-FY2023). At the COLUMBIA Program Semi-Annual IPR held on August 30, 2021, the MDA directed COLUMBIA to be funded to the program baseline, including IEP funding. FY2026 reflects funding to the NAVSEA 05C's 2023 cost estimate (including impacts from inflation) as well as to the results of preliminary Build II contract negotiations for basic construction costs. The Build II preliminary negotiations accounts for anticipated cost growth based on current vendor proposals, current shipbuilder performance, and inflation. The Program is completing an updated cost estimate and CAPE Independent Cost Estimate (ICE) to support Build II contract negotiation and award. The IEP funding leverages Congressional authorities and is aligned to OSD and Navy direction to execute COLUMBIA Class schedules needed to accelerate ship delivery schedules to reduce the strategic deterrence coverage gaps during transition from OHIO SSBNs to CLB SSBNs and the transition from D5LE to D5LE2 missiles. It is crucial to maintain force structure necessary to meet USSTRATCOM requirements for Sea-Based Strategic Deterrence (SBSD). Total MIB funding of $1,352M in FY2026 is accounted for in SSBN 837 Plans Costs P-5c Cost Category to ensure it is visible and can be appropriately tracked and managed. Since the FY2025 submission, FY2026 was reduced by $50M and rephased later into the FYDP FY2021 was the year of authorization for the lead ship, DISTRICT OF COLUMBIA (SSBN 826), and was a new start program due to FY2021 being the first year of incremental full funding. FY2022 and FY2023 were the second and third year of full funding for lead ship, DISTRICT OF COLUMBIA. FY2024 was the year of authorization for the second ship, WISCONSIN (SSBN 827), and first year of incremental funding for the second ship; FY2025 is the second year of incremental funding. FY2026 will be the year of authorization and the first year of incremental funding for the third ship. The budget request supports continued detailed design and construction of CFE and GFE systems to build, test, outfit, and deliver SSBN 828 and later ships. Funding also supports Continuous Production of Missile Tubes, Advance Construction (AC), EOQ for Multi-Program Procurement, Continuous Production of Shipyard Manufactured Items, and Supplier Development to reduce COLUMBIA Class construction schedule risk executed in accordance with enhanced acquisition authorities contained within the National Sea-Based Deterrence Fund (NSBDF), 10 U.S.C. 2218a. The Navy executed a Build I contract for the first two COLUMBIA class submarines (SSBN 826 and SSBN 827), detailed below. The Navy's FY2026 budget was altered to reflect three-year incremental funding profile for all COLUMBIA (CLB) Build II Ships and continues for rest of class. This results in a reduction of $3.1B in FY2026 (shifted into follow years). This incremental full funding profile supports the phased requirements to meet the objective SSBN 828 delivery date. A Contract Modification for ongoing design/advance construction efforts was awarded on 22 June 2020, which also included the Build I Option for the First Two Ships. This was a Pre-Priced Option for the two ships, SSBN 826 and SSBN 827, and associated design/support efforts. This was a modification of the current IPPD contract (N00024-17-C-2117) and is in line with the program's approved Acquisition Strategy. The program received authorization for SSBN 826 in FY2021, funded with three years of incremental funding in FY2021-2023, and SSBN 827 was authorized in FY2024, funded with two years of incremental funding in FY2024-2025. In December 2022, program awarded an additional pre-priced contract modification of IPPD to support Build II/III Advance Procurement / Advance Construction, EOQ for Build II, and MIB efforts. CLB and VIRGINIA Class (VCS) Programs are executing an innovative contracting approach (similar to CLB Build I) which will coordinate CLB Build II with VCS new construction contracting efforts (VCS FY2024 ships and Block VI (FY2025-2029)) to maximize efficiency and stability across the industrial base. The coordination of three separate contract actions eliminates redundant effort by negotiating multiple contracts simultaneously while allowing the shipbuilders to place material orders for multiple ships in concert with VCS which improves stability for supplier base to de-risk schedules. Since the FY2025 submission, the COLUMBIA Class Program continues investment in initiatives to reduce construction schedule risk and enable cost savings (Multi-Program Material Procurement (MPMP), Continuous Production (CP) of Missile Tubes/Outfitting, Ordnance Systems and Shipyard Manufactured Components, Economic Order Quantity efforts, and Advance Construction). Increased investment in Strategic Weapons System (SWS) Shipboard Systems EOQ and Continuous Production leverages additional opportunities to mitigate obsolescence and construction schedule risks and realize additional cost savings outside of the FYDP. The Navy in FY2026 continues to fund additional IEP initiatives (EOQ/MPMP, CP, Missile Tube Outfitting, AC/AP, and Production Backup Units) which is crucial to de-risk and execute IEP Objective schedules. Total class cost savings is $2,010M. Details are contained in the P-10. The first Missile Tube Module (MTM) is funded through RDTEN Program Element 0603595N for $584M; additional $195M funds added due to MTM performance growth in the FY2026 submission.
A7: SCN | B7: Procurement | D7: COLUMBIA Class Submarine - Net Procurement FY 2026 | E7: 1 | F7: Full ship DD&C | L7: 3928828 | N7: 3928828 | V7: [SUB] | W7: 1045 / COLUMBIA Class Submarine | X7: USN | Y7: Combatant Ships | Z7: Submarines | AA7: SSBN | AB7: P-1 Exhibit > BA 01 > Line 1 Net | AC7: 12 | AF7: 1045 | AI7: Maritime Platforms & Systems | AJ7: Submarines - SSBN/SSGN | AK7: MISSION: Strategic Deterrence. The COLUMBIA Class Program is an Acquisition Category (ACAT) ID Major Defense Acquisition Program (MDAP) to design, construct, and deliver a replacement for the OHIO Class Fleet Ballistic Missile Submarines (SSBNs), which begins retiring at a rate of one per year beginning in 2027. The mission of the COLUMBIA SSBN is to maintain an appropriate state of readiness to assist in deterring nuclear attack on the United States and its allies. In the event deterrence should fail, the force must be capable of launching missiles against pre-planned or adaptively planned targets. To fulfill this mission COLUMBIA SSBNs must be capable of performing extended strategic deterrent patrols without requiring assistance or replenishment. It does not have a requirement for additional capabilities or other missions unrelated to survivable strategic nuclear deterrence. Armament: Torpedo Tubes Ballistic Missile Tubes Major Electronics: Trident D5 Strategic Weapons System Command, Control, Communications and Intelligence System - Open System Architecture - Twenty-three Subsystems Note: The FY 2026 request for COLUMBIA Class Submarine includes $8,994,594 thousand of discretionary funding and $1,925,892 thousand of mandatory (reconciliation) funding for a total of $10,920,486 thousand. While the total FY 2026 discretionary funding decreased by $1,426,814 million when compared to the FY 2026 funding in the FY 2025 submission ($10,421,408 thousand), the overall funding (mandatory plus discretionary) for COLUMBIA Class Submarine increased by $499,078 thousand when compared to the FY 2026 funding in the FY 2025 submission. FY2026 is the first year of incremental full funding for the third ship, SSBN 828. Additionally, FY2026 funds the COLUMBIA Class Program to the NAVSEA 05C's 2023 cost estimate and preliminary Build II (SSBN 828-832) contract negotiations. The FY2026 budget and P5 breakout also includes Cost to Complete for Build I (SSBN 826-827), however, funding is reflected in FY2027-2030. The budget also includes continuing Integrated Enterprise Plan (IEP) funding initiatives, material procurement for future ships, and funding for the Maritime Industrial Base (MIB) (previously referred to as the Submarine Industrial Base/SIB). These MIB investments provide enterprise funding to strengthen the MIB to support a generational increase in submarine demand and includes supplier development, shipbuilder/supplier infrastructure, workforce development, technology opportunities, and strategic outsourcing. Investments are targeted to support uplift of the MIB to achieve a "1+2 " Production Cadence, strengthening the MIB and reprioritizing/growing infrastructure to support new construction goals and increased demand as well as improved maintenance and sustainment for the submarine fleet. The MIB funding profile reflects the funding provided by the Indo-Pacific Supplemental Appropriations Act, 2024 ($1,955M) to support improvements to the MIB. FY2025 Plans includes supplier development Congressional adds +$5M for explosion welding facilities and +$18.5M for tube/propulsor facilitization. In August 2020, the COLUMBIA Class program completed its Construction Authorization In Progress Review (IPR). The Milestone Decision Authority (MDA) approved the program for entry into Build I construction on 28 August 2020, pending FY2021 congressional authorization and appropriation. As a result of the IPR, the FY2022 budget submission reflected SSBN 826-837 requirements aligned to the NAVSEA 05C's 2020 cost estimate plus additional funding for SSBN 826 based on the CAPE Lead Ship Assessment (LSA) cost estimate (+$155M FY2022-FY2023). At the COLUMBIA Program Semi-Annual IPR held on August 30, 2021, the MDA directed COLUMBIA to be funded to the program baseline, including IEP funding. FY2026 reflects funding to the NAVSEA 05C's 2023 cost estimate (including impacts from inflation) as well as to the results of preliminary Build II contract negotiations for basic construction costs. The Build II preliminary negotiations accounts for anticipated cost growth based on current vendor proposals, current shipbuilder performance, and inflation. The Program is completing an updated cost estimate and CAPE Independent Cost Estimate (ICE) to support Build II contract negotiation and award. The IEP funding leverages Congressional authorities and is aligned to OSD and Navy direction to execute COLUMBIA Class schedules needed to accelerate ship delivery schedules to reduce the strategic deterrence coverage gaps during transition from OHIO SSBNs to CLB SSBNs and the transition from D5LE to D5LE2 missiles. It is crucial to maintain force structure necessary to meet USSTRATCOM requirements for Sea-Based Strategic Deterrence (SBSD). Total MIB funding of $1,352M in FY2026 is accounted for in SSBN 837 Plans Costs P-5c Cost Category to ensure it is visible and can be appropriately tracked and managed. Since the FY2025 submission, FY2026 was reduced by $50M and rephased later into the FYDP FY2021 was the year of authorization for the lead ship, DISTRICT OF COLUMBIA (SSBN 826), and was a new start program due to FY2021 being the first year of incremental full funding. FY2022 and FY2023 were the second and third year of full funding for lead ship, DISTRICT OF COLUMBIA. FY2024 was the year of authorization for the second ship, WISCONSIN (SSBN 827), and first year of incremental funding for the second ship; FY2025 is the second year of incremental funding. FY2026 will be the year of authorization and the first year of incremental funding for the third ship. The budget request supports continued detailed design and construction of CFE and GFE systems to build, test, outfit, and deliver SSBN 828 and later ships. Funding also supports Continuous Production of Missile Tubes, Advance Construction (AC), EOQ for Multi-Program Procurement, Continuous Production of Shipyard Manufactured Items, and Supplier Development to reduce COLUMBIA Class construction schedule risk executed in accordance with enhanced acquisition authorities contained within the National Sea-Based Deterrence Fund (NSBDF), 10 U.S.C. 2218a. The Navy executed a Build I contract for the first two COLUMBIA class submarines (SSBN 826 and SSBN 827), detailed below. The Navy's FY2026 budget was altered to reflect three-year incremental funding profile for all COLUMBIA (CLB) Build II Ships and continues for rest of class. This results in a reduction of $3.1B in FY2026 (shifted into follow years). This incremental full funding profile supports the phased requirements to meet the objective SSBN 828 delivery date. A Contract Modification for ongoing design/advance construction efforts was awarded on 22 June 2020, which also included the Build I Option for the First Two Ships. This was a Pre-Priced Option for the two ships, SSBN 826 and SSBN 827, and associated design/support efforts. This was a modification of the current IPPD contract (N00024-17-C-2117) and is in line with the program's approved Acquisition Strategy. The program received authorization for SSBN 826 in FY2021, funded with three years of incremental funding in FY2021-2023, and SSBN 827 was authorized in FY2024, funded with two years of incremental funding in FY2024-2025. In December 2022, program awarded an additional pre-priced contract modification of IPPD to support Build II/III Advance Procurement / Advance Construction, EOQ for Build II, and MIB efforts. CLB and VIRGINIA Class (VCS) Programs are executing an innovative contracting approach (similar to CLB Build I) which will coordinate CLB Build II with VCS new construction contracting efforts (VCS FY2024 ships and Block VI (FY2025-2029)) to maximize efficiency and stability across the industrial base. The coordination of three separate contract actions eliminates redundant effort by negotiating multiple contracts simultaneously while allowing the shipbuilders to place material orders for multiple ships in concert with VCS which improves stability for supplier base to de-risk schedules. Since the FY2025 submission, the COLUMBIA Class Program continues investment in initiatives to reduce construction schedule risk and enable cost savings (Multi-Program Material Procurement (MPMP), Continuous Production (CP) of Missile Tubes/Outfitting, Ordnance Systems and Shipyard Manufactured Components, Economic Order Quantity efforts, and Advance Construction). Increased investment in Strategic Weapons System (SWS) Shipboard Systems EOQ and Continuous Production leverages additional opportunities to mitigate obsolescence and construction schedule risks and realize additional cost savings outside of the FYDP. The Navy in FY2026 continues to fund additional IEP initiatives (EOQ/MPMP, CP, Missile Tube Outfitting, AC/AP, and Production Backup Units) which is crucial to de-risk and execute IEP Objective schedules. Total class cost savings is $2,010M. Details are contained in the P-10. The first Missile Tube Module (MTM) is funded through RDTEN Program Element 0603595N for $584M; additional $195M funds added due to MTM performance growth in the FY2026 submission.
A8: SCN | B8: Procurement | C8: 1045 | D8: COLUMBIA Class Submarine Advance Procurement (CY) | E8: 1 | F8: Advance procurement / LLTM | J8: 6215939 | L8: 5065766 | M8: 1925892 | N8: 6991658 | P8: 0 | Q8: 5350766 | R8: 5350766 | S8: 4763342 | T8: 205700 | U8: 4969042 | X8: USN | Y8: Combatant Ships | Z8: Submarines | AA8: SSBN | AB8: P-40 Exhibit > LI 1045 AP > COLUMBIA Class Submarine Advance Procurement | AC8: 57 | AF8: 1045 | AI8: Maritime Platforms & Systems | AJ8: Submarines - SSBN/SSGN | AK8: MISSION: Strategic Deterrence. The COLUMBIA Class Program is an Acquisition Category (ACAT) ID Major Defense Acquisition Program (MDAP) to design, construct, and deliver a replacement for the OHIO Class Fleet Ballistic Missile Submarines (SSBNs), which begins retiring at a rate of one per year beginning in 2027. The mission of the COLUMBIA SSBN is to maintain an appropriate state of readiness to assist in deterring nuclear attack on the United States and its allies. In the event deterrence should fail, the force must be capable of launching missiles against pre-planned or adaptively planned targets. To fulfill this mission COLUMBIA SSBNs must be capable of performing extended strategic deterrent patrols without requiring assistance or replenishment. It does not have a requirement for additional capabilities or other missions unrelated to survivable strategic nuclear deterrence. Armament: Torpedo Tubes Ballistic Missile Tubes Major Electronics: Trident D5 Strategic Weapons System Command, Control, Communications and Intelligence System - Open System Architecture - Twenty-three Subsystems Note: The FY 2026 request for COLUMBIA Class Submarine includes $8,994,594 thousand of discretionary funding and $1,925,892 thousand of mandatory (reconciliation) funding for a total of $10,920,486 thousand. While the total FY 2026 discretionary funding decreased by $1,426,814 million when compared to the FY 2026 funding in the FY 2025 submission ($10,421,408 thousand), the overall funding (mandatory plus discretionary) for COLUMBIA Class Submarine increased by $499,078 thousand when compared to the FY 2026 funding in the FY 2025 submission. FY2026 is the first year of incremental full funding for the third ship, SSBN 828. Additionally, FY2026 funds the COLUMBIA Class Program to the NAVSEA 05C's 2023 cost estimate and preliminary Build II (SSBN 828-832) contract negotiations. The FY2026 budget and P5 breakout also includes Cost to Complete for Build I (SSBN 826-827), however, funding is reflected in FY2027-2030. The budget also includes continuing Integrated Enterprise Plan (IEP) funding initiatives, material procurement for future ships, and funding for the Maritime Industrial Base (MIB) (previously referred to as the Submarine Industrial Base/SIB). These MIB investments provide enterprise funding to strengthen the MIB to support a generational increase in submarine demand and includes supplier development, shipbuilder/supplier infrastructure, workforce development, technology opportunities, and strategic outsourcing. Investments are targeted to support uplift of the MIB to achieve a "1+2 " Production Cadence, strengthening the MIB and reprioritizing/growing infrastructure to support new construction goals and increased demand as well as improved maintenance and sustainment for the submarine fleet. The MIB funding profile reflects the funding provided by the Indo-Pacific Supplemental Appropriations Act, 2024 ($1,955M) to support improvements to the MIB. FY2025 Plans includes supplier development Congressional adds +$5M for explosion welding facilities and +$18.5M for tube/propulsor facilitization. In August 2020, the COLUMBIA Class program completed its Construction Authorization In Progress Review (IPR). The Milestone Decision Authority (MDA) approved the program for entry into Build I construction on 28 August 2020, pending FY2021 congressional authorization and appropriation. As a result of the IPR, the FY2022 budget submission reflected SSBN 826-837 requirements aligned to the NAVSEA 05C's 2020 cost estimate plus additional funding for SSBN 826 based on the CAPE Lead Ship Assessment (LSA) cost estimate (+$155M FY2022-FY2023). At the COLUMBIA Program Semi-Annual IPR held on August 30, 2021, the MDA directed COLUMBIA to be funded to the program baseline, including IEP funding. FY2026 reflects funding to the NAVSEA 05C's 2023 cost estimate (including impacts from inflation) as well as to the results of preliminary Build II contract negotiations for basic construction costs. The Build II preliminary negotiations accounts for anticipated cost growth based on current vendor proposals, current shipbuilder performance, and inflation. The Program is completing an updated cost estimate and CAPE Independent Cost Estimate (ICE) to support Build II contract negotiation and award. The IEP funding leverages Congressional authorities and is aligned to OSD and Navy direction to execute COLUMBIA Class schedules needed to accelerate ship delivery schedules to reduce the strategic deterrence coverage gaps during transition from OHIO SSBNs to CLB SSBNs and the transition from D5LE to D5LE2 missiles. It is crucial to maintain force structure necessary to meet USSTRATCOM requirements for Sea-Based Strategic Deterrence (SBSD). Total MIB funding of $1,352M in FY2026 is accounted for in SSBN 837 Plans Costs P-5c Cost Category to ensure it is visible and can be appropriately tracked and managed. Since the FY2025 submission, FY2026 was reduced by $50M and rephased later into the FYDP FY2021 was the year of authorization for the lead ship, DISTRICT OF COLUMBIA (SSBN 826), and was a new start program due to FY2021 being the first year of incremental full funding. FY2022 and FY2023 were the second and third year of full funding for lead ship, DISTRICT OF COLUMBIA. FY2024 was the year of authorization for the second ship, WISCONSIN (SSBN 827), and first year of incremental funding for the second ship; FY2025 is the second year of incremental funding. FY2026 will be the year of authorization and the first year of incremental funding for the third ship. The budget request supports continued detailed design and construction of CFE and GFE systems to build, test, outfit, and deliver SSBN 828 and later ships. Funding also supports Continuous Production of Missile Tubes, Advance Construction (AC), EOQ for Multi-Program Procurement, Continuous Production of Shipyard Manufactured Items, and Supplier Development to reduce COLUMBIA Class construction schedule risk executed in accordance with enhanced acquisition authorities contained within the National Sea-Based Deterrence Fund (NSBDF), 10 U.S.C. 2218a. The Navy executed a Build I contract for the first two COLUMBIA class submarines (SSBN 826 and SSBN 827), detailed below. The Navy's FY2026 budget was altered to reflect three-year incremental funding profile for all COLUMBIA (CLB) Build II Ships and continues for rest of class. This results in a reduction of $3.1B in FY2026 (shifted into follow years). This incremental full funding profile supports the phased requirements to meet the objective SSBN 828 delivery date. A Contract Modification for ongoing design/advance construction efforts was awarded on 22 June 2020, which also included the Build I Option for the First Two Ships. This was a Pre-Priced Option for the two ships, SSBN 826 and SSBN 827, and associated design/support efforts. This was a modification of the current IPPD contract (N00024-17-C-2117) and is in line with the program's approved Acquisition Strategy. The program received authorization for SSBN 826 in FY2021, funded with three years of incremental funding in FY2021-2023, and SSBN 827 was authorized in FY2024, funded with two years of incremental funding in FY2024-2025. In December 2022, program awarded an additional pre-priced contract modification of IPPD to support Build II/III Advance Procurement / Advance Construction, EOQ for Build II, and MIB efforts. CLB and VIRGINIA Class (VCS) Programs are executing an innovative contracting approach (similar to CLB Build I) which will coordinate CLB Build II with VCS new construction contracting efforts (VCS FY2024 ships and Block VI (FY2025-2029)) to maximize efficiency and stability across the industrial base. The coordination of three separate contract actions eliminates redundant effort by negotiating multiple contracts simultaneously while allowing the shipbuilders to place material orders for multiple ships in concert with VCS which improves stability for supplier base to de-risk schedules. Since the FY2025 submission, the COLUMBIA Class Program continues investment in initiatives to reduce construction schedule risk and enable cost savings (Multi-Program Material Procurement (MPMP), Continuous Production (CP) of Missile Tubes/Outfitting, Ordnance Systems and Shipyard Manufactured Components, Economic Order Quantity efforts, and Advance Construction). Increased investment in Strategic Weapons System (SWS) Shipboard Systems EOQ and Continuous Production leverages additional opportunities to mitigate obsolescence and construction schedule risks and realize additional cost savings outside of the FYDP. The Navy in FY2026 continues to fund additional IEP initiatives (EOQ/MPMP, CP, Missile Tube Outfitting, AC/AP, and Production Backup Units) which is crucial to de-risk and execute IEP Objective schedules. Total class cost savings is $2,010M. Details are contained in the P-10. The first Missile Tube Module (MTM) is funded through RDTEN Program Element 0603595N for $584M; additional $195M funds added due to MTM performance growth in the FY2026 submission.
A9: SCN | B9: Procurement | C9: 2001 | D9: Carrier Replacement Program | E9: 1 | F9: Full ship DD&C | G9: To provide credible, sustainable, independent forward presence during peacetime without access to land bases; operate as the cornerstone of a joint and/or allied maritime expeditionary force in response to crisis; and carry the war to the enemy through joint multi-mission offensive operations. The | I9: 1729021 | J9: 1359124 | L9: 1046700 | M9: 0 | N9: 1046700 | S9: 641907 | T9: 37000 | U9: 678907 | V9: [PARENT] | X9: USN | Y9: Combatant Ships | Z9: Aircraft Carriers | AA9: CVN | AB9: P-40 Exhibit > LI 2001 > Carrier Replacement Program | AC9: 73 | AF9: 2001 | AI9: Maritime Platforms & Systems | AJ9: Aircraft Carriers | AK9: To provide credible, sustainable, independent forward presence during peacetime without access to land bases; operate as the cornerstone of a joint and/or allied maritime expeditionary force in response to crisis; and carry the war to the enemy through joint multi-mission offensive operations. The Navy designed the FORD Class aircraft carrier with the warfighting capability essential for the 21st century, and the flexibility and resilience to rapidly adapt to emerging threats. The Ford class incorporates advances in technology such as a new reactor plant, propulsion system, electric plant, Electromagnetic Aircraft Launch System (EMALS), Advanced Arresting Gear (AAG), machinery control, and integrated warfare systems that increase lethality, while lowering life cycle costs through reductions in maintenance and manning requirements. Increased Service Life Allowances (SLA) for weight and stability enable future modernization and the ability to adapt to new missions over the ship's 50-year life cycle. CVN 80 and CVN 81 were awarded under a two-ship buy. CVN 80 is a separate contract line item under the same contract as CVN 81, which allows discrete hull costs to be captured. The CVN 80/81 construction contract is a Fixed Price Incentive (Firm Target) (FPIF) contract type that limits the Navy's liability and incentivizes the shipyard's best performance. The contract language guarantees a single technical baseline for both ships, which allows the shipyard to re-use engineering rollover products, minimize changes between the two ships and leverages economic order quantities for equipment and material procurement. The Advanced Procurement (AP) funding in FY 2026 is the first of 4 years of AP funding for CVN 82. CVN 81 was moved to BLI 2004 in accordance with the Department of Defense Appropriations Act, 2020.
A10: SCN | B10: Procurement | D10: Carrier Replacement - SFF for FY 2018 | E10: 1 | F10: Full ship DD&C | I10: 1104421 | J10: 1123124 | L10: 1046700 | N10: 1046700 | V10: [SUB] | W10: 2001 / Carrier Replacement Program | X10: USN | Y10: Combatant Ships | Z10: Aircraft Carriers | AA10: CVN | AB10: P-1 Exhibit > BA 02 > Line 5 SFF | AC10: 15 | AF10: 2001 | AI10: Maritime Platforms & Systems | AJ10: Aircraft Carriers | AK10: To provide credible, sustainable, independent forward presence during peacetime without access to land bases; operate as the cornerstone of a joint and/or allied maritime expeditionary force in response to crisis; and carry the war to the enemy through joint multi-mission offensive operations. The Navy designed the FORD Class aircraft carrier with the warfighting capability essential for the 21st century, and the flexibility and resilience to rapidly adapt to emerging threats. The Ford class incorporates advances in technology such as a new reactor plant, propulsion system, electric plant, Electromagnetic Aircraft Launch System (EMALS), Advanced Arresting Gear (AAG), machinery control, and integrated warfare systems that increase lethality, while lowering life cycle costs through reductions in maintenance and manning requirements. Increased Service Life Allowances (SLA) for weight and stability enable future modernization and the ability to adapt to new missions over the ship's 50-year life cycle. CVN 80 and CVN 81 were awarded under a two-ship buy. CVN 80 is a separate contract line item under the same contract as CVN 81, which allows discrete hull costs to be captured. The CVN 80/81 construction contract is a Fixed Price Incentive (Firm Target) (FPIF) contract type that limits the Navy's liability and incentivizes the shipyard's best performance. The contract language guarantees a single technical baseline for both ships, which allows the shipyard to re-use engineering rollover products, minimize changes between the two ships and leverages economic order quantities for equipment and material procurement. The Advanced Procurement (AP) funding in FY 2026 is the first of 4 years of AP funding for CVN 82. CVN 81 was moved to BLI 2004 in accordance with the Department of Defense Appropriations Act, 2020.
A11: SCN | B11: Procurement | D11: Carrier Replacement - Completion PY FY 2013 | E11: 1 | F11: Full ship DD&C | I11: 624600 | J11: 236000 | V11: [SUB] | W11: 2001 / Carrier Replacement Program | X11: USN | Y11: Combatant Ships | Z11: Aircraft Carriers | AA11: CVN | AB11: P-1 Exhibit > BA 02 > Line 5 CTC | AC11: 15 | AF11: 2001 | AI11: Maritime Platforms & Systems | AJ11: Aircraft Carriers | AK11: To provide credible, sustainable, independent forward presence during peacetime without access to land bases; operate as the cornerstone of a joint and/or allied maritime expeditionary force in response to crisis; and carry the war to the enemy through joint multi-mission offensive operations. The Navy designed the FORD Class aircraft carrier with the warfighting capability essential for the 21st century, and the flexibility and resilience to rapidly adapt to emerging threats. The Ford class incorporates advances in technology such as a new reactor plant, propulsion system, electric plant, Electromagnetic Aircraft Launch System (EMALS), Advanced Arresting Gear (AAG), machinery control, and integrated warfare systems that increase lethality, while lowering life cycle costs through reductions in maintenance and manning requirements. Increased Service Life Allowances (SLA) for weight and stability enable future modernization and the ability to adapt to new missions over the ship's 50-year life cycle. CVN 80 and CVN 81 were awarded under a two-ship buy. CVN 80 is a separate contract line item under the same contract as CVN 81, which allows discrete hull costs to be captured. The CVN 80/81 construction contract is a Fixed Price Incentive (Firm Target) (FPIF) contract type that limits the Navy's liability and incentivizes the shipyard's best performance. The contract language guarantees a single technical baseline for both ships, which allows the shipyard to re-use engineering rollover products, minimize changes between the two ships and leverages economic order quantities for equipment and material procurement. The Advanced Procurement (AP) funding in FY 2026 is the first of 4 years of AP funding for CVN 82. CVN 81 was moved to BLI 2004 in accordance with the Department of Defense Appropriations Act, 2020.
A12: SCN | B12: Procurement | C12: 2001 | D12: Carrier Replacement Program Advance Procurement (CY) | E12: 1 | F12: Advance procurement / LLTM | G12: Basic: Funding is required for procurement of the longest lead non-reactor propulsion plant, electric plant contractor furnished equipment and shipbuilder advance procurement / construction efforts necessary to support an efficient CVN 82 construction schedule. Advance Construction (AC) / Advance | L12: 612038 | M12: 0 | N12: 612038 | Q12: 612038 | R12: 612038 | S12: 1940566 | U12: 1940566 | X12: USN | Y12: Combatant Ships | Z12: Aircraft Carriers | AA12: CVN | AB12: P-40 Exhibit > LI 2001 AP > Carrier Replacement AP | AC12: 115 | AF12: 2001 | AI12: Maritime Platforms & Systems | AJ12: Aircraft Carriers | AK12: To provide credible, sustainable, independent forward presence during peacetime without access to land bases; operate as the cornerstone of a joint and/or allied maritime expeditionary force in response to crisis; and carry the war to the enemy through joint multi-mission offensive operations. The Navy designed the FORD Class aircraft carrier with the warfighting capability essential for the 21st century, and the flexibility and resilience to rapidly adapt to emerging threats. The Ford class incorporates advances in technology such as a new reactor plant, propulsion system, electric plant, Electromagnetic Aircraft Launch System (EMALS), Advanced Arresting Gear (AAG), machinery control, and integrated warfare systems that increase lethality, while lowering life cycle costs through reductions in maintenance and manning requirements. Increased Service Life Allowances (SLA) for weight and stability enable future modernization and the ability to adapt to new missions over the ship's 50-year life cycle. CVN 80 and CVN 81 were awarded under a two-ship buy. CVN 80 is a separate contract line item under the same contract as CVN 81, which allows discrete hull costs to be captured. The CVN 80/81 construction contract is a Fixed Price Incentive (Firm Target) (FPIF) contract type that limits the Navy's liability and incentivizes the shipyard's best performance. The contract language guarantees a single technical baseline for both ships, which allows the shipyard to re-use engineering rollover products, minimize changes between the two ships and leverages economic order quantities for equipment and material procurement. The Advanced Procurement (AP) funding in FY 2026 is the first of 4 years of AP funding for CVN 82. CVN 81 was moved to BLI 2004 in accordance with the Department of Defense Appropriations Act, 2020.
A13: SCN | B13: Procurement | C13: 2004 | D13: CVN-81 | E13: 1 | F13: Full ship DD&C | G13: To provide credible, sustainable, independent forward presence during peacetime without access to land bases; operate as the cornerstone of a joint and/or allied maritime expeditionary force in response to crisis; and carry the war to the enemy through joint multi-mission offensive operations. The | I13: 800492 | J13: 674930 | L13: 1622935 | M13: 0 | N13: 1622935 | S13: 1447882 | U13: 1447882 | X13: USN | Y13: Combatant Ships | Z13: Aircraft Carriers | AA13: CVN | AB13: P-40 Exhibit > LI 2004 > CVN-81 | AC13: 117 | AF13: 2004 | AI13: Maritime Platforms & Systems | AJ13: Aircraft Carriers | AK13: To provide credible, sustainable, independent forward presence during peacetime without access to land bases; operate as the cornerstone of a joint and/or allied maritime expeditionary force in response to crisis; and carry the war to the enemy through joint multi-mission offensive operations. The Navy designed the FORD Class aircraft carrier with the warfighting capability essential for the 21st century, and the flexibility and resilience to rapidly adapt to emerging threats. The Ford class incorporates advances in technology such as a new reactor plant, propulsion system, electric plant, Electromagnetic Aircraft Launch System (EMALS), Advanced Arresting Gear (AAG), machinery control, and integrated warfare systems that increase lethality, while lowering life cycle costs through reductions in maintenance and manning requirements. Increased Service Life Allowances (SLA) for weight and stability enable future modernization and the ability to adapt to new missions over the ship's 50-year life cycle. CVN 80 and CVN 81 were awarded under a two-ship buy. CVN 81 is a separate contract line item under the same contract as CVN 80, which allows discrete hull costs to be captured. The CVN 80/81 construction contract is a Fixed Price Incentive (Firm Target) (FPIF) contract type that limits the Navy's liability and incentivizes the shipyard's best performance. The contract language guarantees a single technical baseline for both ships, which allows the shipyard to re-use engineering rollover products, minimize changes between the two ships and leverages economic order quantities for equipment and material procurement.
A14: SCN | B14: Procurement | C14: 2013 | D14: Virginia Class Submarine | E14: 1 | F14: Full ship DD&C | G14: MISSION: To seek out and destroy enemy ships across a wide spectrum of tactical scenarios, working both independently and in concert with a battle group/other ships, providing Joint Commanders with early, accurate knowledge of the battlefield on which power may be projected from sea; covert | I14: 7298145 | J14: 9599908 | L14: 816705 | M14: 6518600 | N14: 7335305 | P14: 4600000 | Q14: 2740305 | R14: 7340305 | S14: 8402316 | U14: 8402316 | V14: [PARENT] | X14: USN | Y14: Combatant Ships | Z14: Submarines | AA14: SSN | AB14: P-40 Exhibit > LI 2013 > Virginia Class Submarine | AC14: 155 | AF14: 2013 | AI14: Maritime Platforms & Systems | AJ14: Submarines - SSN | AK14: MISSION: To seek out and destroy enemy ships across a wide spectrum of tactical scenarios, working both independently and in concert with a battle group/other ships, providing Joint Commanders with early, accurate knowledge of the battlefield on which power may be projected from sea; covert striking power against targets ashore; the capability to establish covertly an expeditionary force on land; and the maritime strength to destroy enemy naval forces and interdict seaborne commerce. NOTE: For VIRGINIA Class Submarine (VCS), the Department requests a total of $11,078,029 thousand and a total quantity of 2 ships. This request includes $3,943,521 thousand of discretionary and a quantity of 1 and $7,134,508 thousand and a quantity of 1 of mandatory for a total of $11,078,029 thousand and a quantity of 2. The mandatory funds one FY 2026 VCS as well as continued investments in nuclear shipbuilder productivity wage enhancements. The discretionary includes funds for one FY 2026 VCS, and advance procurement and economic order quantity funds for future VIRGINIA Class Submarines. Further information for this reconciliation request is provided in Section 20002 (Shipbuilding) of the Reconciliation Exhibit. The program is currently executing the fourth Multi-Year Procurement (MYP) (Block V) contract which was awarded on 2 December 2019, modified on 22 March 2021 to exercise an option for a tenth SSN, and subsequently modified on 30 April 2025 to include the FY 2024 eleventh and twelfth SSNs. The April 2025 modification includes funds received via the American Relief Act (ARA) of 2025 (H.R.10545) to support construction of the FY 2024 hulls ($1,950M) and FY 2025 hull ($1,528M), as well as investments in shipbuilder workforce support and infrastructure enhancements ($2,213M). Block V incorporates Acoustic Superiority (AS) modifications on all SSNs, and VIRGINIA Payload Module (VPM) beginning with SSN 803. All Block V SSNs will include modifications to provide enhanced capability and improved performance based upon efforts performed via RDT&E (PE 0604558N/Prj 1947). VPM is an 84-foot hull section with four additional payload tubes, each capable of carrying seven Tomahawk cruise missiles or various other payloads. VPM helps mitigate the loss of undersea strike capability with the retirement of the Service's four guided missile submarines (SSGNs) in the late-2020s. Funding associated with these changes to the baseline are shown in more detail on subsequent pages of these exhibits. The program is currently planning the fifth MYP (Block VI) contract for FY 2025 - FY 2029 procurements.
A15: SCN | B15: Procurement | D15: Virginia Class Sub - Net Procurement | E15: 1 | F15: Full ship DD&C | I15: 7129965 | J15: 7356904 | L15: 816705 | M15: 6518600 | N15: 7335305 | V15: [SUB] | W15: 2013 / Virginia Class Submarine | X15: USN | Y15: Combatant Ships | Z15: Submarines | AA15: SSN | AB15: P-1 Exhibit > BA 02 > Line 8 Net | AC15: 14 | AF15: 2013 | AI15: Maritime Platforms & Systems | AJ15: Submarines - SSN | AK15: MISSION: To seek out and destroy enemy ships across a wide spectrum of tactical scenarios, working both independently and in concert with a battle group/other ships, providing Joint Commanders with early, accurate knowledge of the battlefield on which power may be projected from sea; covert striking power against targets ashore; the capability to establish covertly an expeditionary force on land; and the maritime strength to destroy enemy naval forces and interdict seaborne commerce. NOTE: For VIRGINIA Class Submarine (VCS), the Department requests a total of $11,078,029 thousand and a total quantity of 2 ships. This request includes $3,943,521 thousand of discretionary and a quantity of 1 and $7,134,508 thousand and a quantity of 1 of mandatory for a total of $11,078,029 thousand and a quantity of 2. The mandatory funds one FY 2026 VCS as well as continued investments in nuclear shipbuilder productivity wage enhancements. The discretionary includes funds for one FY 2026 VCS, and advance procurement and economic order quantity funds for future VIRGINIA Class Submarines. Further information for this reconciliation request is provided in Section 20002 (Shipbuilding) of the Reconciliation Exhibit. The program is currently executing the fourth Multi-Year Procurement (MYP) (Block V) contract which was awarded on 2 December 2019, modified on 22 March 2021 to exercise an option for a tenth SSN, and subsequently modified on 30 April 2025 to include the FY 2024 eleventh and twelfth SSNs. The April 2025 modification includes funds received via the American Relief Act (ARA) of 2025 (H.R.10545) to support construction of the FY 2024 hulls ($1,950M) and FY 2025 hull ($1,528M), as well as investments in shipbuilder workforce support and infrastructure enhancements ($2,213M). Block V incorporates Acoustic Superiority (AS) modifications on all SSNs, and VIRGINIA Payload Module (VPM) beginning with SSN 803. All Block V SSNs will include modifications to provide enhanced capability and improved performance based upon efforts performed via RDT&E (PE 0604558N/Prj 1947). VPM is an 84-foot hull section with four additional payload tubes, each capable of carrying seven Tomahawk cruise missiles or various other payloads. VPM helps mitigate the loss of undersea strike capability with the retirement of the Service's four guided missile submarines (SSGNs) in the late-2020s. Funding associated with these changes to the baseline are shown in more detail on subsequent pages of these exhibits. The program is currently planning the fifth MYP (Block VI) contract for FY 2025 - FY 2029 procurements.
A16: SCN | B16: Procurement | D16: Virginia Class Sub - SFF for FY 2024 | E16: 1 | F16: Full ship DD&C | J16: 1950000 | V16: [SUB] | W16: 2013 / Virginia Class Submarine | X16: USN | Y16: Combatant Ships | Z16: Submarines | AA16: SSN | AB16: P-1 Exhibit > BA 02 > Line 8 SFF | AC16: 14 | AF16: 2013 | AI16: Maritime Platforms & Systems | AJ16: Submarines - SSN | AK16: MISSION: To seek out and destroy enemy ships across a wide spectrum of tactical scenarios, working both independently and in concert with a battle group/other ships, providing Joint Commanders with early, accurate knowledge of the battlefield on which power may be projected from sea; covert striking power against targets ashore; the capability to establish covertly an expeditionary force on land; and the maritime strength to destroy enemy naval forces and interdict seaborne commerce. NOTE: For VIRGINIA Class Submarine (VCS), the Department requests a total of $11,078,029 thousand and a total quantity of 2 ships. This request includes $3,943,521 thousand of discretionary and a quantity of 1 and $7,134,508 thousand and a quantity of 1 of mandatory for a total of $11,078,029 thousand and a quantity of 2. The mandatory funds one FY 2026 VCS as well as continued investments in nuclear shipbuilder productivity wage enhancements. The discretionary includes funds for one FY 2026 VCS, and advance procurement and economic order quantity funds for future VIRGINIA Class Submarines. Further information for this reconciliation request is provided in Section 20002 (Shipbuilding) of the Reconciliation Exhibit. The program is currently executing the fourth Multi-Year Procurement (MYP) (Block V) contract which was awarded on 2 December 2019, modified on 22 March 2021 to exercise an option for a tenth SSN, and subsequently modified on 30 April 2025 to include the FY 2024 eleventh and twelfth SSNs. The April 2025 modification includes funds received via the American Relief Act (ARA) of 2025 (H.R.10545) to support construction of the FY 2024 hulls ($1,950M) and FY 2025 hull ($1,528M), as well as investments in shipbuilder workforce support and infrastructure enhancements ($2,213M). Block V incorporates Acoustic Superiority (AS) modifications on all SSNs, and VIRGINIA Payload Module (VPM) beginning with SSN 803. All Block V SSNs will include modifications to provide enhanced capability and improved performance based upon efforts performed via RDT&E (PE 0604558N/Prj 1947). VPM is an 84-foot hull section with four additional payload tubes, each capable of carrying seven Tomahawk cruise missiles or various other payloads. VPM helps mitigate the loss of undersea strike capability with the retirement of the Service's four guided missile submarines (SSGNs) in the late-2020s. Funding associated with these changes to the baseline are shown in more detail on subsequent pages of these exhibits. The program is currently planning the fifth MYP (Block VI) contract for FY 2025 - FY 2029 procurements.
A17: SCN | B17: Procurement | D17: Virginia Class Sub - Completion PY (FY15-18) | E17: 1 | F17: Full ship DD&C | I17: 168180 | J17: 293004 | V17: [SUB] | W17: 2013 / Virginia Class Submarine | X17: USN | Y17: Combatant Ships | Z17: Submarines | AA17: SSN | AB17: P-1 Exhibit > BA 02 > Line 8 CTC | AC17: 14 | AF17: 2013 | AI17: Maritime Platforms & Systems | AJ17: Submarines - SSN | AK17: MISSION: To seek out and destroy enemy ships across a wide spectrum of tactical scenarios, working both independently and in concert with a battle group/other ships, providing Joint Commanders with early, accurate knowledge of the battlefield on which power may be projected from sea; covert striking power against targets ashore; the capability to establish covertly an expeditionary force on land; and the maritime strength to destroy enemy naval forces and interdict seaborne commerce. NOTE: For VIRGINIA Class Submarine (VCS), the Department requests a total of $11,078,029 thousand and a total quantity of 2 ships. This request includes $3,943,521 thousand of discretionary and a quantity of 1 and $7,134,508 thousand and a quantity of 1 of mandatory for a total of $11,078,029 thousand and a quantity of 2. The mandatory funds one FY 2026 VCS as well as continued investments in nuclear shipbuilder productivity wage enhancements. The discretionary includes funds for one FY 2026 VCS, and advance procurement and economic order quantity funds for future VIRGINIA Class Submarines. Further information for this reconciliation request is provided in Section 20002 (Shipbuilding) of the Reconciliation Exhibit. The program is currently executing the fourth Multi-Year Procurement (MYP) (Block V) contract which was awarded on 2 December 2019, modified on 22 March 2021 to exercise an option for a tenth SSN, and subsequently modified on 30 April 2025 to include the FY 2024 eleventh and twelfth SSNs. The April 2025 modification includes funds received via the American Relief Act (ARA) of 2025 (H.R.10545) to support construction of the FY 2024 hulls ($1,950M) and FY 2025 hull ($1,528M), as well as investments in shipbuilder workforce support and infrastructure enhancements ($2,213M). Block V incorporates Acoustic Superiority (AS) modifications on all SSNs, and VIRGINIA Payload Module (VPM) beginning with SSN 803. All Block V SSNs will include modifications to provide enhanced capability and improved performance based upon efforts performed via RDT&E (PE 0604558N/Prj 1947). VPM is an 84-foot hull section with four additional payload tubes, each capable of carrying seven Tomahawk cruise missiles or various other payloads. VPM helps mitigate the loss of undersea strike capability with the retirement of the Service's four guided missile submarines (SSGNs) in the late-2020s. Funding associated with these changes to the baseline are shown in more detail on subsequent pages of these exhibits. The program is currently planning the fifth MYP (Block VI) contract for FY 2025 - FY 2029 procurements.
A18: SCN | B18: Procurement | C18: 2013 | D18: Virginia Class Submarine Advance Procurement (CY) | E18: 1 | F18: Advance procurement / LLTM | G18: The Total Ship estimate for the FY 2025 hull includes additional funds in support of critical spare material that will be consumed on future hulls to ensure critical sub-tier vendors maintain two per year cadence. Advance Procurement and EOQ funds essential Long Lead Time materials to meet in yard | I18: 3358782 | J18: 3720303 | L18: 3126816 | M18: 615908 | N18: 3742724 | P18: 0 | Q18: 3126816 | R18: 3126816 | S18: 4143618 | T18: 1440000 | U18: 5583618 | X18: USN | Y18: Combatant Ships | Z18: Submarines | AA18: SSN | AB18: P-40 Exhibit > LI 2013 AP > Virginia Class Sub AP | AC18: 171 | AF18: 2013 | AI18: Maritime Platforms & Systems | AJ18: Submarines - SSN | AK18: MISSION: To seek out and destroy enemy ships across a wide spectrum of tactical scenarios, working both independently and in concert with a battle group/other ships, providing Joint Commanders with early, accurate knowledge of the battlefield on which power may be projected from sea; covert striking power against targets ashore; the capability to establish covertly an expeditionary force on land; and the maritime strength to destroy enemy naval forces and interdict seaborne commerce. NOTE: For VIRGINIA Class Submarine (VCS), the Department requests a total of $11,078,029 thousand and a total quantity of 2 ships. This request includes $3,943,521 thousand of discretionary and a quantity of 1 and $7,134,508 thousand and a quantity of 1 of mandatory for a total of $11,078,029 thousand and a quantity of 2. The mandatory funds one FY 2026 VCS as well as continued investments in nuclear shipbuilder productivity wage enhancements. The discretionary includes funds for one FY 2026 VCS, and advance procurement and economic order quantity funds for future VIRGINIA Class Submarines. Further information for this reconciliation request is provided in Section 20002 (Shipbuilding) of the Reconciliation Exhibit. The program is currently executing the fourth Multi-Year Procurement (MYP) (Block V) contract which was awarded on 2 December 2019, modified on 22 March 2021 to exercise an option for a tenth SSN, and subsequently modified on 30 April 2025 to include the FY 2024 eleventh and twelfth SSNs. The April 2025 modification includes funds received via the American Relief Act (ARA) of 2025 (H.R.10545) to support construction of the FY 2024 hulls ($1,950M) and FY 2025 hull ($1,528M), as well as investments in shipbuilder workforce support and infrastructure enhancements ($2,213M). Block V incorporates Acoustic Superiority (AS) modifications on all SSNs, and VIRGINIA Payload Module (VPM) beginning with SSN 803. All Block V SSNs will include modifications to provide enhanced capability and improved performance based upon efforts performed via RDT&E (PE 0604558N/Prj 1947). VPM is an 84-foot hull section with four additional payload tubes, each capable of carrying seven Tomahawk cruise missiles or various other payloads. VPM helps mitigate the loss of undersea strike capability with the retirement of the Service's four guided missile submarines (SSGNs) in the late-2020s. Funding associated with these changes to the baseline are shown in more detail on subsequent pages of these exhibits. The program is currently planning the fifth MYP (Block VI) contract for FY 2025 - FY 2029 procurements.
A19: SCN | B19: Procurement | C19: 2086 | D19: CVN Refueling Overhauls | E19: 5 | F19: RCOH | G19: To support and operate aircraft to engage in attacks on targets afloat and ashore which threaten our use of the sea and to engage in sustained operations in support of other forces. The refueling of the reactors and repair and upgrade of the main propulsion equipment will provide for reliable | I19: 42422 | J19: 1480314 | L19: 1779011 | M19: 0 | N19: 1779011 | Q19: 1579011 | R19: 1579011 | S19: 4418902 | T19: 30000 | U19: 4448902 | V19: [PARENT] | X19: USN | Y19: Combatant Ships | Z19: Aircraft Carriers | AA19: CVN | AB19: P-40 Exhibit > LI 2086 > CVN Refueling Overhauls | AC19: 175 | AF19: 2086 | AI19: Maritime Sustainment & Lifecycle Support | AJ19: Nuclear Refueling Overhaul (NNSY) | AK19: To support and operate aircraft to engage in attacks on targets afloat and ashore which threaten our use of the sea and to engage in sustained operations in support of other forces. The refueling of the reactors and repair and upgrade of the main propulsion equipment will provide for reliable operations during its remaining 23 plus years of ship life using only the normal maintenance cycle.
A20: SCN | B20: Procurement | D20: CVN Refueling - Net Procurement FY 2025 | E20: 5 | F20: RCOH | J20: 811143 | V20: [SUB] | W20: 2086 / CVN Refueling Overhauls | X20: USN | Y20: Combatant Ships | Z20: Aircraft Carriers | AA20: CVN | AB20: P-1 Exhibit > BA 02 > Line 10 Net | AC20: 14 | AF20: 2086 | AI20: Maritime Sustainment & Lifecycle Support | AJ20: Nuclear Refueling Overhaul (NNSY) | AK20: To support and operate aircraft to engage in attacks on targets afloat and ashore which threaten our use of the sea and to engage in sustained operations in support of other forces. The refueling of the reactors and repair and upgrade of the main propulsion equipment will provide for reliable operations during its remaining 23 plus years of ship life using only the normal maintenance cycle.
A21: SCN | B21: Procurement | D21: CVN Refueling - SFF for FY 2025 | E21: 5 | F21: RCOH | L21: 1779011 | N21: 1779011 | V21: [SUB] | W21: 2086 / CVN Refueling Overhauls | X21: USN | Y21: Combatant Ships | Z21: Aircraft Carriers | AA21: CVN | AB21: P-1 Exhibit > BA 02 > Line 10 SFF | AC21: 14 | AF21: 2086 | AI21: Maritime Sustainment & Lifecycle Support | AJ21: Nuclear Refueling Overhaul (NNSY) | AK21: To support and operate aircraft to engage in attacks on targets afloat and ashore which threaten our use of the sea and to engage in sustained operations in support of other forces. The refueling of the reactors and repair and upgrade of the main propulsion equipment will provide for reliable operations during its remaining 23 plus years of ship life using only the normal maintenance cycle.
A22: SCN | B22: Procurement | D22: CVN Refueling - Completion PY FY 2020 | E22: 5 | F22: RCOH | I22: 42422 | J22: 669171 | V22: [SUB] | W22: 2086 / CVN Refueling Overhauls | X22: USN | Y22: Combatant Ships | Z22: Aircraft Carriers | AA22: CVN | AB22: P-1 Exhibit > BA 02 > Line 10 CTC | AC22: 14 | AF22: 2086 | AI22: Maritime Sustainment & Lifecycle Support | AJ22: Nuclear Refueling Overhaul (NNSY) | AK22: To support and operate aircraft to engage in attacks on targets afloat and ashore which threaten our use of the sea and to engage in sustained operations in support of other forces. The refueling of the reactors and repair and upgrade of the main propulsion equipment will provide for reliable operations during its remaining 23 plus years of ship life using only the normal maintenance cycle.
A23: SCN | B23: Procurement | C23: 2086 | D23: CVN Refueling Overhauls Advance Procurement (CY) | E23: 5 | F23: RCOH | G23: No advance procurement funds requested for RCOH in FY 2026. *Note: "When Required" is the number of months required before ship delivery. | I23: 488446 | J23: 0 | L23: 0 | M23: 0 | N23: 0 | S23: 53070 | U23: 53070 | X23: USN | Y23: Combatant Ships | Z23: Aircraft Carriers | AA23: CVN | AB23: P-40 Exhibit > LI 2086 AP > CVN Refueling AP | AC23: 209 | AF23: 2086 | AI23: Maritime Sustainment & Lifecycle Support | AJ23: Nuclear Refueling Overhaul (NNSY) | AK23: To support and operate aircraft to engage in attacks on targets afloat and ashore which threaten our use of the sea and to engage in sustained operations in support of other forces. The refueling of the reactors and repair and upgrade of the main propulsion equipment will provide for reliable operations during its remaining 23 plus years of ship life using only the normal maintenance cycle.
A24: SCN | B24: Procurement | C24: 2119 | D24: DDG 1000 | E24: 1 | F24: Full ship DD&C | G24: DDG 1000, a multi-mission surface combatant, will serve as a versatile asset in the context of future Naval Strategy. Armed with an array of weapons, DDG 1000 will provide the Joint Force Commander with precision strike and volume fires. Designed with sustainable payload, multi-spectral stealth and | I24: 392892 | J24: 61100 | L24: 52358 | M24: 0 | N24: 52358 | Q24: 52358 | R24: 52358 | S24: 66516 | U24: 66516 | X24: USN | Y24: Combatant Ships | Z24: Surface Combatants | AA24: DDG | AB24: P-40 Exhibit > LI 2119 > DDG 1000 | AC24: 211 | AF24: 2119 | AI24: Maritime Platforms & Systems | AJ24: Surface Combatants - Large | AK24: DDG 1000, a multi-mission surface combatant, will serve as a versatile asset in the context of future Naval Strategy. Armed with an array of weapons, DDG 1000 will provide the Joint Force Commander with precision strike and volume fires. Designed with sustainable payload, multi-spectral stealth and optimal manning, DDG 1000 will take the fight to the enemy with unprecedented striking power. The program continues to integrate the Conventional Prompt Strike (CPS) weapons system on the DDG 1000 Class. CPS installation on the lead ship by Q1 FY25 and all three ships in the class by Q4 FY28. DDG 1000 will be the first maritime platform to integrate the CPS weapons system. This naval surface hypersonic strike capability will conduct independent forward deployed operations and prosecute deep-inland, time-critical, soft and medium-hardened targets in a contested environment. The CPS capability, combined with the low observable characteristics of the ZUMWALT platform, creates a uniquely lethal and survivable naval surface platform. ZUMWALT Class enhances U.S. conventional power projection by providing an independent forward deployed strike platform, with longer range, shorter time of flight, and higher survivability against enemy defenses compared to current capabilities. CPS integration on Lyndon B. Johnson (DDG 1002) will occur during new construction, prior to the ship's arrival in homeport and prior to installation of CPS on DDG 1001. Full CPS operational capability on ZUMWALT Class is achieved when CPS is installed on all three ships and they are turned over for Fleet operations. DDG 1000 and DDG 1001 are delivered/commissioned ships. The CPS installations for these ships is budgeted with Other Procurement, Navy (OPN LI 0947) funding. DDG 1002 CPS installation is budgeted in Shipbuilding and Conversion, Navy funding.
A25: SCN | B25: Procurement | C25: 2122 | D25: DDG-51 | E25: 1 | F25: Full ship DD&C | G25: DDG 51 will be able to operate offensively and defensively, independently or as units of Carrier Strike Groups and Surface Action Groups, in support of Marine Amphibious Task Forces in multi-threat environments that include air, surface and subsurface threats. These ships will respond to Low | I25: 4725096 | J25: 8185404 | L25: 10773 | M25: 5400000 | N25: 5410773 | P25: 5400000 | Q25: 10773 | R25: 5410773 | S25: 2954238 | T25: 314000 | U25: 3268238 | V25: [PARENT] | X25: USN | Y25: Combatant Ships | Z25: Surface Combatants | AA25: DDG | AB25: P-40 Exhibit > LI 2122 > DDG-51 | AC25: 237 | AF25: 2122 | AI25: Maritime Platforms & Systems | AJ25: Surface Combatants - Large | AK25: DDG 51 will be able to operate offensively and defensively, independently or as units of Carrier Strike Groups and Surface Action Groups, in support of Marine Amphibious Task Forces in multi-threat environments that include air, surface and subsurface threats. These ships will respond to Low Intensity Conflict/Coastal and Littoral Offshore Warfare (LIC/CALOW) scenarios as well as open ocean conflict providing or augmenting power projection and forward presence requirements, and escort operations at sea. Beginning in FY17, DDG 51 Flight III with the Air and Missile Defense Radar (SPY-6(V)1) will significantly enhance Integrated Air and Missile Defense capability against current and future threats. Starting in FY22, DDG 51 Flight III AN/SLQ-32 system is upgraded from AN/SLQ-32(V)6 to AN/SLQ-32(V)7, with the addition of SEWIP Block 3, which provides advanced Electronic Attack (EA) capability to keep pace with the evolving Anti-Ship Missile (ASM) threat and counter-targeting. Starting in FY23, the MK38 Gun Weapon System is being upgraded to the Mod 4 configuration and transitions from a post construction to an in-line installation, the WSN-7 inertial navigation system is being replaced with the follow-on WSN-12 navigation system, 15 additional berths are being introduced, and the Bridgemaster Surface Search Radar is being replaced by the Next-Generation Surface Search Radar (NGSSR). For the DDG 51 Program, the Department requests a total of $5,410,773 thousand and a total quantity of two. This request includes includes $10,773 thousand and quantity of 0 of discretionary funding and $5,410,000 thousand and quantity of 2 of mandatory funding for a total FY 2026 request of $5,410,773 thousand and quantity of 2. The mandatory and discretionary funds support the contract award for two FY 2026 ships. Further information for this reconciliation request will be provided in Section 20002 (Shipbuilding) of the Reconciliation Exhibit. Note: (1) The FY 2018-2022 acquisition strategy is a 10 ship Multi-year Procurement (MYP) with options. This budget request reflects savings for the ships in FY 2018-FY 2022 associated with EOQ procurement and a MYP strategy. Additional ships in FY 2019 and FY 2020 also reflect quantity savings over annual ship prices. (2) The Navy awarded two Multi-year Procurement (MYP) contracts for FY 2023 - FY 2027 for 9 ships with options. This budget request reflects savings for the ships in FY 2023-FY 2027 associated with EOQ procurement and a MYP strategy. The additional ships in FY 2023 and FY 2025 also reflect quantity savings over annual ship prices. (3) FY 2025 includes subsequent year full funding for the following: $923,808K for FY 2023 ships and $759,563K for FY 2024 ships.
A26: SCN | B26: Procurement | D26: DDG-51 - Net Procurement | E26: 1 | F26: Full ship DD&C | I26: 4499179 | J26: 6268519 | L26: 10773 | M26: 5400000 | N26: 5410773 | V26: [SUB] | W26: 2122 / DDG-51 | X26: USN | Y26: Combatant Ships | Z26: Surface Combatants | AA26: DDG | AB26: P-1 Exhibit > BA 02 > Line 13 Net | AC26: 14 | AF26: 2122 | AI26: Maritime Platforms & Systems | AJ26: Surface Combatants - Large | AK26: DDG 51 will be able to operate offensively and defensively, independently or as units of Carrier Strike Groups and Surface Action Groups, in support of Marine Amphibious Task Forces in multi-threat environments that include air, surface and subsurface threats. These ships will respond to Low Intensity Conflict/Coastal and Littoral Offshore Warfare (LIC/CALOW) scenarios as well as open ocean conflict providing or augmenting power projection and forward presence requirements, and escort operations at sea. Beginning in FY17, DDG 51 Flight III with the Air and Missile Defense Radar (SPY-6(V)1) will significantly enhance Integrated Air and Missile Defense capability against current and future threats. Starting in FY22, DDG 51 Flight III AN/SLQ-32 system is upgraded from AN/SLQ-32(V)6 to AN/SLQ-32(V)7, with the addition of SEWIP Block 3, which provides advanced Electronic Attack (EA) capability to keep pace with the evolving Anti-Ship Missile (ASM) threat and counter-targeting. Starting in FY23, the MK38 Gun Weapon System is being upgraded to the Mod 4 configuration and transitions from a post construction to an in-line installation, the WSN-7 inertial navigation system is being replaced with the follow-on WSN-12 navigation system, 15 additional berths are being introduced, and the Bridgemaster Surface Search Radar is being replaced by the Next-Generation Surface Search Radar (NGSSR). For the DDG 51 Program, the Department requests a total of $5,410,773 thousand and a total quantity of two. This request includes includes $10,773 thousand and quantity of 0 of discretionary funding and $5,410,000 thousand and quantity of 2 of mandatory funding for a total FY 2026 request of $5,410,773 thousand and quantity of 2. The mandatory and discretionary funds support the contract award for two FY 2026 ships. Further information for this reconciliation request will be provided in Section 20002 (Shipbuilding) of the Reconciliation Exhibit. Note: (1) The FY 2018-2022 acquisition strategy is a 10 ship Multi-year Procurement (MYP) with options. This budget request reflects savings for the ships in FY 2018-FY 2022 associated with EOQ procurement and a MYP strategy. Additional ships in FY 2019 and FY 2020 also reflect quantity savings over annual ship prices. (2) The Navy awarded two Multi-year Procurement (MYP) contracts for FY 2023 - FY 2027 for 9 ships with options. This budget request reflects savings for the ships in FY 2023-FY 2027 associated with EOQ procurement and a MYP strategy. The additional ships in FY 2023 and FY 2025 also reflect quantity savings over annual ship prices. (3) FY 2025 includes subsequent year full funding for the following: $923,808K for FY 2023 ships and $759,563K for FY 2024 ships.
A27: SCN | B27: Procurement | D27: DDG-51 - SFF for FY 2023 and FY 2024 | E27: 1 | F27: Full ship DD&C | J27: 1683371 | V27: [SUB] | W27: 2122 / DDG-51 | X27: USN | Y27: Combatant Ships | Z27: Surface Combatants | AA27: DDG | AB27: P-1 Exhibit > BA 02 > Line 13 SFF | AC27: 15 | AF27: 2122 | AI27: Maritime Platforms & Systems | AJ27: Surface Combatants - Large | AK27: DDG 51 will be able to operate offensively and defensively, independently or as units of Carrier Strike Groups and Surface Action Groups, in support of Marine Amphibious Task Forces in multi-threat environments that include air, surface and subsurface threats. These ships will respond to Low Intensity Conflict/Coastal and Littoral Offshore Warfare (LIC/CALOW) scenarios as well as open ocean conflict providing or augmenting power projection and forward presence requirements, and escort operations at sea. Beginning in FY17, DDG 51 Flight III with the Air and Missile Defense Radar (SPY-6(V)1) will significantly enhance Integrated Air and Missile Defense capability against current and future threats. Starting in FY22, DDG 51 Flight III AN/SLQ-32 system is upgraded from AN/SLQ-32(V)6 to AN/SLQ-32(V)7, with the addition of SEWIP Block 3, which provides advanced Electronic Attack (EA) capability to keep pace with the evolving Anti-Ship Missile (ASM) threat and counter-targeting. Starting in FY23, the MK38 Gun Weapon System is being upgraded to the Mod 4 configuration and transitions from a post construction to an in-line installation, the WSN-7 inertial navigation system is being replaced with the follow-on WSN-12 navigation system, 15 additional berths are being introduced, and the Bridgemaster Surface Search Radar is being replaced by the Next-Generation Surface Search Radar (NGSSR). For the DDG 51 Program, the Department requests a total of $5,410,773 thousand and a total quantity of two. This request includes includes $10,773 thousand and quantity of 0 of discretionary funding and $5,410,000 thousand and quantity of 2 of mandatory funding for a total FY 2026 request of $5,410,773 thousand and quantity of 2. The mandatory and discretionary funds support the contract award for two FY 2026 ships. Further information for this reconciliation request will be provided in Section 20002 (Shipbuilding) of the Reconciliation Exhibit. Note: (1) The FY 2018-2022 acquisition strategy is a 10 ship Multi-year Procurement (MYP) with options. This budget request reflects savings for the ships in FY 2018-FY 2022 associated with EOQ procurement and a MYP strategy. Additional ships in FY 2019 and FY 2020 also reflect quantity savings over annual ship prices. (2) The Navy awarded two Multi-year Procurement (MYP) contracts for FY 2023 - FY 2027 for 9 ships with options. This budget request reflects savings for the ships in FY 2023-FY 2027 associated with EOQ procurement and a MYP strategy. The additional ships in FY 2023 and FY 2025 also reflect quantity savings over annual ship prices. (3) FY 2025 includes subsequent year full funding for the following: $923,808K for FY 2023 ships and $759,563K for FY 2024 ships.
A28: SCN | B28: Procurement | D28: DDG-51 - Completion PY (FY16-18) | E28: 1 | F28: Full ship DD&C | I28: 225917 | J28: 233514 | V28: [SUB] | W28: 2122 / DDG-51 | X28: USN | Y28: Combatant Ships | Z28: Surface Combatants | AA28: DDG | AB28: P-1 Exhibit > BA 02 > Line 13 CTC | AC28: 14 | AF28: 2122 | AI28: Maritime Platforms & Systems | AJ28: Surface Combatants - Large | AK28: DDG 51 will be able to operate offensively and defensively, independently or as units of Carrier Strike Groups and Surface Action Groups, in support of Marine Amphibious Task Forces in multi-threat environments that include air, surface and subsurface threats. These ships will respond to Low Intensity Conflict/Coastal and Littoral Offshore Warfare (LIC/CALOW) scenarios as well as open ocean conflict providing or augmenting power projection and forward presence requirements, and escort operations at sea. Beginning in FY17, DDG 51 Flight III with the Air and Missile Defense Radar (SPY-6(V)1) will significantly enhance Integrated Air and Missile Defense capability against current and future threats. Starting in FY22, DDG 51 Flight III AN/SLQ-32 system is upgraded from AN/SLQ-32(V)6 to AN/SLQ-32(V)7, with the addition of SEWIP Block 3, which provides advanced Electronic Attack (EA) capability to keep pace with the evolving Anti-Ship Missile (ASM) threat and counter-targeting. Starting in FY23, the MK38 Gun Weapon System is being upgraded to the Mod 4 configuration and transitions from a post construction to an in-line installation, the WSN-7 inertial navigation system is being replaced with the follow-on WSN-12 navigation system, 15 additional berths are being introduced, and the Bridgemaster Surface Search Radar is being replaced by the Next-Generation Surface Search Radar (NGSSR). For the DDG 51 Program, the Department requests a total of $5,410,773 thousand and a total quantity of two. This request includes includes $10,773 thousand and quantity of 0 of discretionary funding and $5,410,000 thousand and quantity of 2 of mandatory funding for a total FY 2026 request of $5,410,773 thousand and quantity of 2. The mandatory and discretionary funds support the contract award for two FY 2026 ships. Further information for this reconciliation request will be provided in Section 20002 (Shipbuilding) of the Reconciliation Exhibit. Note: (1) The FY 2018-2022 acquisition strategy is a 10 ship Multi-year Procurement (MYP) with options. This budget request reflects savings for the ships in FY 2018-FY 2022 associated with EOQ procurement and a MYP strategy. Additional ships in FY 2019 and FY 2020 also reflect quantity savings over annual ship prices. (2) The Navy awarded two Multi-year Procurement (MYP) contracts for FY 2023 - FY 2027 for 9 ships with options. This budget request reflects savings for the ships in FY 2023-FY 2027 associated with EOQ procurement and a MYP strategy. The additional ships in FY 2023 and FY 2025 also reflect quantity savings over annual ship prices. (3) FY 2025 includes subsequent year full funding for the following: $923,808K for FY 2023 ships and $759,563K for FY 2024 ships.
A29: SCN | B29: Procurement | C29: 2122 | D29: DDG-51 Advance Procurement (CY) | E29: 1 | F29: Advance procurement / LLTM | G29: There is no FY 2026 Advance Procurement request in mandatory ($0 thousand) or discretionary ($0 thousand) funding. FY23 - FY24 AP is required for shipbuilder and AEGIS Weapon System (AWS) Economic Order Quantity procurements for material items to achieve savings for the FY23-FY27 MYP ships. FY24 - | I29: 1641335 | J29: 83224 | L29: 0 | M29: 0 | N29: 0 | Q29: 1750000 | R29: 1750000 | X29: USN | Y29: Combatant Ships | Z29: Surface Combatants | AA29: DDG | AB29: P-40 Exhibit > LI 2122 AP > DDG-51 AP | AC29: 265 | AF29: 2122 | AI29: Maritime Platforms & Systems | AJ29: Surface Combatants - Large | AK29: DDG 51 will be able to operate offensively and defensively, independently or as units of Carrier Strike Groups and Surface Action Groups, in support of Marine Amphibious Task Forces in multi-threat environments that include air, surface and subsurface threats. These ships will respond to Low Intensity Conflict/Coastal and Littoral Offshore Warfare (LIC/CALOW) scenarios as well as open ocean conflict providing or augmenting power projection and forward presence requirements, and escort operations at sea. Beginning in FY17, DDG 51 Flight III with the Air and Missile Defense Radar (SPY-6(V)1) will significantly enhance Integrated Air and Missile Defense capability against current and future threats. Starting in FY22, DDG 51 Flight III AN/SLQ-32 system is upgraded from AN/SLQ-32(V)6 to AN/SLQ-32(V)7, with the addition of SEWIP Block 3, which provides advanced Electronic Attack (EA) capability to keep pace with the evolving Anti-Ship Missile (ASM) threat and counter-targeting. Starting in FY23, the MK38 Gun Weapon System is being upgraded to the Mod 4 configuration and transitions from a post construction to an in-line installation, the WSN-7 inertial navigation system is being replaced with the follow-on WSN-12 navigation system, 15 additional berths are being introduced, and the Bridgemaster Surface Search Radar is being replaced by the Next-Generation Surface Search Radar (NGSSR). For the DDG 51 Program, the Department requests a total of $5,410,773 thousand and a total quantity of two. This request includes includes $10,773 thousand and quantity of 0 of discretionary funding and $5,410,000 thousand and quantity of 2 of mandatory funding for a total FY 2026 request of $5,410,773 thousand and quantity of 2. The mandatory and discretionary funds support the contract award for two FY 2026 ships. Further information for this reconciliation request will be provided in Section 20002 (Shipbuilding) of the Reconciliation Exhibit. Note: (1) The FY 2018-2022 acquisition strategy is a 10 ship Multi-year Procurement (MYP) with options. This budget request reflects savings for the ships in FY 2018-FY 2022 associated with EOQ procurement and a MYP strategy. Additional ships in FY 2019 and FY 2020 also reflect quantity savings over annual ship prices. (2) The Navy awarded two Multi-year Procurement (MYP) contracts for FY 2023 - FY 2027 for 9 ships with options. This budget request reflects savings for the ships in FY 2023-FY 2027 associated with EOQ procurement and a MYP strategy. The additional ships in FY 2023 and FY 2025 also reflect quantity savings over annual ship prices. (3) FY 2025 includes subsequent year full funding for the following: $923,808K for FY 2023 ships and $759,563K for FY 2024 ships.
A30: SCN | B30: Procurement | C30: 2127 | D30: Littoral Combat Ship (LCS) | E30: 1 | F30: Full ship DD&C | G30: Provides for the design, construction, integration, and testing of the Littoral Combat Ship (LCS) including ordnance, government furnished equipment (GFE), plans and change order costs. LCS deploys focused-mission packages to execute surface warfare (SUW) and mine countermeasures (MCM) operations. | I30: 23000 | J30: 48000 | L30: 0 | M30: 0 | N30: 0 | X30: USN | Y30: Combatant Ships | Z30: Surface Combatants | AA30: LCS | AB30: P-40 Exhibit > LI 2127 > Littoral Combat Ship | AC30: 269 | AF30: 2127 | AI30: Maritime Platforms & Systems | AJ30: Surface Combatants - Medium | AK30: Provides for the design, construction, integration, and testing of the Littoral Combat Ship (LCS) including ordnance, government furnished equipment (GFE), plans and change order costs. LCS deploys focused-mission packages to execute surface warfare (SUW) and mine countermeasures (MCM) operations. LCS also possesses inherent capabilities, regardless of the mission package installed, including intelligence, surveillance, and reconnaissance (ISR), anti-terrorism/force protection (AT/FP), air warfare self-defense, joint littoral mobility, and logistic support for movement of personnel and supplies. LCS SUW ships will also include maritime interdiction/interception operations (MIO). LCS MCM ships will incorporate unmanned vehicles to conduct mine hunting and mine sweeping missions. This relatively small, shallow-draft, high-speed surface combatant complements the U.S. Navy's Surface Fleet by operating in environments where it is impossible or undesirable to employ larger deeper-draft, multi-mission ships. LCS can deploy independently to overseas littoral regions or remain on station for extended periods of time either with a battle group or through a forward-basing arrangement. LCS will operate with Carrier Strike Groups, Surface Action Groups, or independently as dictated by the mission and environment. Additionally, LCS can operate cooperatively with the U.S. Coast Guard and Allies.
A31: SCN | B31: Procurement | C31: 2128 | D31: FFG-Frigate | E31: 1 | F31: Full ship DD&C | G31: The Guided Missile Frigate (FFG 62 Class) is a more lethal and survivable multi-mission small surface combatant. With the FFG 62 Class, the Navy will maximize the small surface combatant capabilities in the Anti-Surface Warfare (SUW), Anti-Submarine Warfare (ASW), Electronic Warfare/Information | I31: 2183861 | J31: 633200 | L31: 0 | M31: 0 | N31: 0 | Q31: 242000 | R31: 242000 | X31: USN | Y31: Combatant Ships | Z31: Surface Combatants | AA31: FFG | AB31: P-40 Exhibit > LI 2128 > FFG-Frigate | AC31: 273 | AF31: 2128 | AI31: Maritime Platforms & Systems | AJ31: Surface Combatants - Medium | AK31: The Guided Missile Frigate (FFG 62 Class) is a more lethal and survivable multi-mission small surface combatant. With the FFG 62 Class, the Navy will maximize the small surface combatant capabilities in the Anti-Surface Warfare (SUW), Anti-Submarine Warfare (ASW), Electronic Warfare/Information Operations (EW/IO), Air Warfare (AW) mission areas, and survivability while keeping the ship affordable and as a part of a "high-low" mix of surface ships. The FFG 62 Class Capability Development Document was JROC approved in Feb 2019 and completed Milestone B, an informed Independent Cost Estimate, and award of the Detail Design & Construction contract in April 2020. Delivery dates reflect the most recent Master Planning Schedule that reflects known programmatic schedule delays.
A32: SCN | B32: Procurement | C32: 3010 | D32: LPD Flight II | E32: 1 | F32: Full ship DD&C | G32: For the LPD Flight II Program, the Department requests a total of $2,600,000 thousand and a total quantity of one. This request includes $0 thousand of discretionary funding and $2,600,000 thousand and quantity of 1 of mandatory funding for a total FY 2026 request of $2,600,000 thousand and a | I32: 0 | J32: 1581121 | L32: 0 | M32: 2325000 | N32: 2325000 | P32: 835037 | Q32: 0 | R32: 835037 | S32: 2188700 | T32: 4000 | U32: 2192700 | V32: [PARENT] | X32: USN | Y32: Combatant Ships | Z32: Amphibious Warfare Ships | AA32: LPD | AB32: P-40 Exhibit > LI 3010 > LPD Flight II | AC32: 303 | AF32: 3010 | AI32: Maritime Platforms & Systems | AJ32: Amphibious Ships | AK32: For the LPD Flight II Program, the Department requests a total of $2,600,000 thousand and a total quantity of one. This request includes $0 thousand of discretionary funding and $2,600,000 thousand and quantity of 1 of mandatory funding for a total FY 2026 request of $2,600,000 thousand and a quantity of 1. The mandatory funds support the contract award of one FY 2026 ship, LPD 34 ($2,129,963 thousand), incremental funding for the FY 2025 ship, LPD 33 ($195,037 thousand), and Advance Procurement for the future LPD 35 ($275,000 thousand). Further information for this reconciliation request will be provided in Section 20002 (Shipbuilding) of the Reconciliation Exhibit. The LPD 17 Flight II is expected to functionally replace LSD-41 Class ships and LSD-49 Class ships for embark, transport, control, insert, sustainment, and extract of Marine Air-Ground Task Force elements and supporting forces by helicopters, landing craft, and amphibious vehicles. Per signed Acquisition Decision Memorandum, LPD 17 Flight II will meet the Capabilities Development Document for LX(R) and shall subsume all previous LX(R) efforts. Name change endorsed in JROCM 093-21, from "Amphibious Ship Replacement LX(R)" to "LPD 17 San Antonio Class Amphibious Transport Dock FLT II." LPD 30 is the first ship of LPD 17 Flight II. The Navy has awarded a Multi-Ship Procurement (MSP) contract in September 2024 for 3 ships (LPD 33, 34, and 35). In total, the 4-ship agreement was awarded simultaneously for LHA 10 and LPD 33-35 and included Advanced Procurement (AP) to acquire Long Lead Time Material (LLTM) and full funding.
A33: SCN | B33: Procurement | D33: LPD Flight II - Net Procurement | E33: 1 | F33: Full ship DD&C | J33: 1561963 | M33: 2129963 | N33: 2129963 | V33: [SUB] | W33: 3010 / LPD Flight II | X33: USN | Y33: Combatant Ships | Z33: Amphibious Warfare Ships | AA33: LPD | AB33: P-1 Exhibit > BA 03 > Line 19 Net | AC33: 18 | AF33: 3010 | AI33: Maritime Platforms & Systems | AJ33: Amphibious Ships | AK33: For the LPD Flight II Program, the Department requests a total of $2,600,000 thousand and a total quantity of one. This request includes $0 thousand of discretionary funding and $2,600,000 thousand and quantity of 1 of mandatory funding for a total FY 2026 request of $2,600,000 thousand and a quantity of 1. The mandatory funds support the contract award of one FY 2026 ship, LPD 34 ($2,129,963 thousand), incremental funding for the FY 2025 ship, LPD 33 ($195,037 thousand), and Advance Procurement for the future LPD 35 ($275,000 thousand). Further information for this reconciliation request will be provided in Section 20002 (Shipbuilding) of the Reconciliation Exhibit. The LPD 17 Flight II is expected to functionally replace LSD-41 Class ships and LSD-49 Class ships for embark, transport, control, insert, sustainment, and extract of Marine Air-Ground Task Force elements and supporting forces by helicopters, landing craft, and amphibious vehicles. Per signed Acquisition Decision Memorandum, LPD 17 Flight II will meet the Capabilities Development Document for LX(R) and shall subsume all previous LX(R) efforts. Name change endorsed in JROCM 093-21, from "Amphibious Ship Replacement LX(R)" to "LPD 17 San Antonio Class Amphibious Transport Dock FLT II." LPD 30 is the first ship of LPD 17 Flight II. The Navy has awarded a Multi-Ship Procurement (MSP) contract in September 2024 for 3 ships (LPD 33, 34, and 35). In total, the 4-ship agreement was awarded simultaneously for LHA 10 and LPD 33-35 and included Advanced Procurement (AP) to acquire Long Lead Time Material (LLTM) and full funding.
A34: SCN | B34: Procurement | D34: LPD Flight II - SFF for FY 2025 | E34: 1 | F34: Full ship DD&C | L34: 0 | M34: 195037 | N34: 195037 | V34: [SUB] | W34: 3010 / LPD Flight II | X34: USN | Y34: Combatant Ships | Z34: Amphibious Warfare Ships | AA34: LPD | AB34: P-1 Exhibit > BA 03 > Line 19 SFF | AC34: 18 | AF34: 3010 | AI34: Maritime Platforms & Systems | AJ34: Amphibious Ships | AK34: For the LPD Flight II Program, the Department requests a total of $2,600,000 thousand and a total quantity of one. This request includes $0 thousand of discretionary funding and $2,600,000 thousand and quantity of 1 of mandatory funding for a total FY 2026 request of $2,600,000 thousand and a quantity of 1. The mandatory funds support the contract award of one FY 2026 ship, LPD 34 ($2,129,963 thousand), incremental funding for the FY 2025 ship, LPD 33 ($195,037 thousand), and Advance Procurement for the future LPD 35 ($275,000 thousand). Further information for this reconciliation request will be provided in Section 20002 (Shipbuilding) of the Reconciliation Exhibit. The LPD 17 Flight II is expected to functionally replace LSD-41 Class ships and LSD-49 Class ships for embark, transport, control, insert, sustainment, and extract of Marine Air-Ground Task Force elements and supporting forces by helicopters, landing craft, and amphibious vehicles. Per signed Acquisition Decision Memorandum, LPD 17 Flight II will meet the Capabilities Development Document for LX(R) and shall subsume all previous LX(R) efforts. Name change endorsed in JROCM 093-21, from "Amphibious Ship Replacement LX(R)" to "LPD 17 San Antonio Class Amphibious Transport Dock FLT II." LPD 30 is the first ship of LPD 17 Flight II. The Navy has awarded a Multi-Ship Procurement (MSP) contract in September 2024 for 3 ships (LPD 33, 34, and 35). In total, the 4-ship agreement was awarded simultaneously for LHA 10 and LPD 33-35 and included Advanced Procurement (AP) to acquire Long Lead Time Material (LLTM) and full funding.
A35: SCN | B35: Procurement | D35: LPD Flight II - Completion PY FY 2018 | E35: 1 | F35: Full ship DD&C | J35: 19158 | V35: [SUB] | W35: 3010 / LPD Flight II | X35: USN | Y35: Combatant Ships | Z35: Amphibious Warfare Ships | AA35: LPD | AB35: P-1 Exhibit > BA 03 > Line 19 CTC | AC35: 18 | AF35: 3010 | AI35: Maritime Platforms & Systems | AJ35: Amphibious Ships | AK35: For the LPD Flight II Program, the Department requests a total of $2,600,000 thousand and a total quantity of one. This request includes $0 thousand of discretionary funding and $2,600,000 thousand and quantity of 1 of mandatory funding for a total FY 2026 request of $2,600,000 thousand and a quantity of 1. The mandatory funds support the contract award of one FY 2026 ship, LPD 34 ($2,129,963 thousand), incremental funding for the FY 2025 ship, LPD 33 ($195,037 thousand), and Advance Procurement for the future LPD 35 ($275,000 thousand). Further information for this reconciliation request will be provided in Section 20002 (Shipbuilding) of the Reconciliation Exhibit. The LPD 17 Flight II is expected to functionally replace LSD-41 Class ships and LSD-49 Class ships for embark, transport, control, insert, sustainment, and extract of Marine Air-Ground Task Force elements and supporting forces by helicopters, landing craft, and amphibious vehicles. Per signed Acquisition Decision Memorandum, LPD 17 Flight II will meet the Capabilities Development Document for LX(R) and shall subsume all previous LX(R) efforts. Name change endorsed in JROCM 093-21, from "Amphibious Ship Replacement LX(R)" to "LPD 17 San Antonio Class Amphibious Transport Dock FLT II." LPD 30 is the first ship of LPD 17 Flight II. The Navy has awarded a Multi-Ship Procurement (MSP) contract in September 2024 for 3 ships (LPD 33, 34, and 35). In total, the 4-ship agreement was awarded simultaneously for LHA 10 and LPD 33-35 and included Advanced Procurement (AP) to acquire Long Lead Time Material (LLTM) and full funding.
A36: SCN | B36: Procurement | C36: 3010 | D36: LPD Flight II Advance Procurement (CY) | E36: 1 | F36: Advance procurement / LLTM | G36: Advance Procurement funding will be used to purchase Long Lead Time Material (LLTM) and to maintain schedule. LLTM procurements will include, but are not limited to: Engines, Diesel Generators, Reduction Gears, Motor Controllers, Propellers, Shafting, Elevators, A/C Plants, Switchboards/Power | I36: 500000 | J36: 0 | L36: 0 | M36: 275000 | N36: 275000 | S36: 355950 | U36: 355950 | X36: USN | Y36: Combatant Ships | Z36: Amphibious Warfare Ships | AA36: LPD | AB36: P-40 Exhibit > LI 3010 AP > LPD Flight II AP | AC36: 321 | AF36: 3010 | AI36: Maritime Platforms & Systems | AJ36: Amphibious Ships | AK36: For the LPD Flight II Program, the Department requests a total of $2,600,000 thousand and a total quantity of one. This request includes $0 thousand of discretionary funding and $2,600,000 thousand and quantity of 1 of mandatory funding for a total FY 2026 request of $2,600,000 thousand and a quantity of 1. The mandatory funds support the contract award of one FY 2026 ship, LPD 34 ($2,129,963 thousand), incremental funding for the FY 2025 ship, LPD 33 ($195,037 thousand), and Advance Procurement for the future LPD 35 ($275,000 thousand). Further information for this reconciliation request will be provided in Section 20002 (Shipbuilding) of the Reconciliation Exhibit. The LPD 17 Flight II is expected to functionally replace LSD-41 Class ships and LSD-49 Class ships for embark, transport, control, insert, sustainment, and extract of Marine Air-Ground Task Force elements and supporting forces by helicopters, landing craft, and amphibious vehicles. Per signed Acquisition Decision Memorandum, LPD 17 Flight II will meet the Capabilities Development Document for LX(R) and shall subsume all previous LX(R) efforts. Name change endorsed in JROCM 093-21, from "Amphibious Ship Replacement LX(R)" to "LPD 17 San Antonio Class Amphibious Transport Dock FLT II." LPD 30 is the first ship of LPD 17 Flight II. The Navy has awarded a Multi-Ship Procurement (MSP) contract in September 2024 for 3 ships (LPD 33, 34, and 35). In total, the 4-ship agreement was awarded simultaneously for LHA 10 and LPD 33-35 and included Advanced Procurement (AP) to acquire Long Lead Time Material (LLTM) and full funding.
A37: SCN | B37: Procurement | D37: LPD-17 | E37: 1 | F37: Full ship DD&C | I37: 16520 | J37: 0 | L37: 0 | M37: 0 | N37: 0 | X37: USN | Y37: Combatant Ships | Z37: Amphibious Warfare Ships | AA37: LPD | AB37: P-1 Exhibit > BA 03 > Line 21 | AC37: 18
A38: SCN | B38: Procurement | C38: 3041 | D38: LHA Replacement | E38: 1 | F38: Full ship DD&C | G38: For the LHA(R) Program, the Department requests a total of $3,895,000 thousand and a total quantity of one. This request includes $0 thousand of discretionary funding and $3,895,000 thousand and quantity of 1 of mandatory funding for a total FY 2026 request of $3,895,000 thousand and a quantity of | I38: 1830149 | J38: 115397 | L38: 0 | M38: 3895000 | N38: 3895000 | P38: 634963 | Q38: 0 | R38: 634963 | S38: 3850319 | T38: 2000 | U38: 3852319 | V38: [PARENT] | X38: USN | Y38: Combatant Ships | Z38: Amphibious Warfare Ships | AA38: LHA | AB38: P-40 Exhibit > LI 3041 > LHA Replacement | AC38: 323 | AF38: 3041 | AI38: Maritime Platforms & Systems | AJ38: Amphibious Ships | AK38: For the LHA(R) Program, the Department requests a total of $3,895,000 thousand and a total quantity of one. This request includes $0 thousand of discretionary funding and $3,895,000 thousand and quantity of 1 of mandatory funding for a total FY 2026 request of $3,895,000 thousand and a quantity of 1. The mandatory funds support the contract award of one FY 2026 ship, LHA 10. Further information for this reconciliation request will be provided in Section 20002 (Shipbuilding) of the Reconciliation Exhibit. The LHA(R) Program replaces the Tarawa Class (LHA 1) Amphibious Assault Class Ships and the retiring Wasp Class (LHD 1) Amphibious Assault Class Ships. The LHA(R) Class Program ensures that the Amphibious Fleet remains capable of Expeditionary Warfare well into the 21st Century and provides for an affordable and sustainable Amphibious Ship development program. The LHA(R) Class provides forward presence and power projection as an integral part of joint, interagency, and multinational maritime Expeditionary forces. The LHA(R) Class operates for sustained periods in transit to and operations in an Amphibious Objective Area to include the embarkation, deployment, and landing of a Marine Landing Force and supporting forces by helicopters and tilt rotors supported by Joint Strike Fighters (JSF) F-35B. LHA(R) Flight 0 is considered a transitional increment intended to increase the aviation capabilities of Amphibious Assault Class Ships. LHA(R) Flight 0 consisted of two ships - LHA 6 and LHA 7. LHA(R) Flight 1 is the second increment in the LHA 6 Class, with LHA 8 (FY 2017) being the first ship of Flight 1. The LHA(R) Flight 1 design continues the incremental development of Amphibious Assault Class Ships by adding a well deck and increasing the flight deck capacity by reducing the footprint of the island and adding a sponson. The Flight 1 ships maintain an aviation centric capability with the addition of a well deck that will accommodate two Landing Craft, Air Cushion (LCAC) vehicles. LHA 9 (FY 2023) is the second LHA(R) Flight 1 ship and assumes a LHA 8 baseline design.
A39: SCN | B39: Procurement | D39: LHA Replacement - SFF for FY 2023 | E39: 1 | F39: Full ship DD&C | I39: 1830149 | V39: [SUB] | W39: 3041 / LHA Replacement | X39: USN | Y39: Combatant Ships | Z39: Amphibious Warfare Ships | AA39: LHA | AB39: P-1 Exhibit > BA 03 > Line 24 SFF | AC39: 18 | AF39: 3041 | AI39: Maritime Platforms & Systems | AJ39: Amphibious Ships | AK39: For the LHA(R) Program, the Department requests a total of $3,895,000 thousand and a total quantity of one. This request includes $0 thousand of discretionary funding and $3,895,000 thousand and quantity of 1 of mandatory funding for a total FY 2026 request of $3,895,000 thousand and a quantity of 1. The mandatory funds support the contract award of one FY 2026 ship, LHA 10. Further information for this reconciliation request will be provided in Section 20002 (Shipbuilding) of the Reconciliation Exhibit. The LHA(R) Program replaces the Tarawa Class (LHA 1) Amphibious Assault Class Ships and the retiring Wasp Class (LHD 1) Amphibious Assault Class Ships. The LHA(R) Class Program ensures that the Amphibious Fleet remains capable of Expeditionary Warfare well into the 21st Century and provides for an affordable and sustainable Amphibious Ship development program. The LHA(R) Class provides forward presence and power projection as an integral part of joint, interagency, and multinational maritime Expeditionary forces. The LHA(R) Class operates for sustained periods in transit to and operations in an Amphibious Objective Area to include the embarkation, deployment, and landing of a Marine Landing Force and supporting forces by helicopters and tilt rotors supported by Joint Strike Fighters (JSF) F-35B. LHA(R) Flight 0 is considered a transitional increment intended to increase the aviation capabilities of Amphibious Assault Class Ships. LHA(R) Flight 0 consisted of two ships - LHA 6 and LHA 7. LHA(R) Flight 1 is the second increment in the LHA 6 Class, with LHA 8 (FY 2017) being the first ship of Flight 1. The LHA(R) Flight 1 design continues the incremental development of Amphibious Assault Class Ships by adding a well deck and increasing the flight deck capacity by reducing the footprint of the island and adding a sponson. The Flight 1 ships maintain an aviation centric capability with the addition of a well deck that will accommodate two Landing Craft, Air Cushion (LCAC) vehicles. LHA 9 (FY 2023) is the second LHA(R) Flight 1 ship and assumes a LHA 8 baseline design.
A40: SCN | B40: Procurement | D40: LHA Replacement - Completion PY FY 2017 | E40: 1 | F40: Full ship DD&C | J40: 115397 | V40: [SUB] | W40: 3041 / LHA Replacement | X40: USN | Y40: Combatant Ships | Z40: Amphibious Warfare Ships | AA40: LHA | AB40: P-1 Exhibit > BA 03 > Line 24 CTC | AC40: 18 | AF40: 3041 | AI40: Maritime Platforms & Systems | AJ40: Amphibious Ships | AK40: For the LHA(R) Program, the Department requests a total of $3,895,000 thousand and a total quantity of one. This request includes $0 thousand of discretionary funding and $3,895,000 thousand and quantity of 1 of mandatory funding for a total FY 2026 request of $3,895,000 thousand and a quantity of 1. The mandatory funds support the contract award of one FY 2026 ship, LHA 10. Further information for this reconciliation request will be provided in Section 20002 (Shipbuilding) of the Reconciliation Exhibit. The LHA(R) Program replaces the Tarawa Class (LHA 1) Amphibious Assault Class Ships and the retiring Wasp Class (LHD 1) Amphibious Assault Class Ships. The LHA(R) Class Program ensures that the Amphibious Fleet remains capable of Expeditionary Warfare well into the 21st Century and provides for an affordable and sustainable Amphibious Ship development program. The LHA(R) Class provides forward presence and power projection as an integral part of joint, interagency, and multinational maritime Expeditionary forces. The LHA(R) Class operates for sustained periods in transit to and operations in an Amphibious Objective Area to include the embarkation, deployment, and landing of a Marine Landing Force and supporting forces by helicopters and tilt rotors supported by Joint Strike Fighters (JSF) F-35B. LHA(R) Flight 0 is considered a transitional increment intended to increase the aviation capabilities of Amphibious Assault Class Ships. LHA(R) Flight 0 consisted of two ships - LHA 6 and LHA 7. LHA(R) Flight 1 is the second increment in the LHA 6 Class, with LHA 8 (FY 2017) being the first ship of Flight 1. The LHA(R) Flight 1 design continues the incremental development of Amphibious Assault Class Ships by adding a well deck and increasing the flight deck capacity by reducing the footprint of the island and adding a sponson. The Flight 1 ships maintain an aviation centric capability with the addition of a well deck that will accommodate two Landing Craft, Air Cushion (LCAC) vehicles. LHA 9 (FY 2023) is the second LHA(R) Flight 1 ship and assumes a LHA 8 baseline design.
A41: SCN | B41: Procurement | C41: 3041 | D41: LHA Replacement Advance Procurement (CY) | E41: 1 | F41: Advance procurement / LLTM | G41: There is no FY 2026 Advance Procurement request in mandatory ($0 thousand) or discretionary ($0 thousand) funding. Advance Procurement funding will be used to purchase Long Lead Time Material (LLTM) and maintain production schedule. LLTM procurements will include, but not be limited to, Port Deck | J41: 61118 | L41: 0 | M41: 0 | N41: 0 | X41: USN | Y41: Combatant Ships | Z41: Amphibious Warfare Ships | AA41: LHA | AB41: P-40 Exhibit > LI 3041 AP > LHA Replacement AP | AC41: 351 | AF41: 3041 | AH41: Basic Construction | AI41: Maritime Platforms & Systems | AJ41: Amphibious Ships | AK41: For the LHA(R) Program, the Department requests a total of $3,895,000 thousand and a total quantity of one. This request includes $0 thousand of discretionary funding and $3,895,000 thousand and quantity of 1 of mandatory funding for a total FY 2026 request of $3,895,000 thousand and a quantity of 1. The mandatory funds support the contract award of one FY 2026 ship, LHA 10. Further information for this reconciliation request will be provided in Section 20002 (Shipbuilding) of the Reconciliation Exhibit. The LHA(R) Program replaces the Tarawa Class (LHA 1) Amphibious Assault Class Ships and the retiring Wasp Class (LHD 1) Amphibious Assault Class Ships. The LHA(R) Class Program ensures that the Amphibious Fleet remains capable of Expeditionary Warfare well into the 21st Century and provides for an affordable and sustainable Amphibious Ship development program. The LHA(R) Class provides forward presence and power projection as an integral part of joint, interagency, and multinational maritime Expeditionary forces. The LHA(R) Class operates for sustained periods in transit to and operations in an Amphibious Objective Area to include the embarkation, deployment, and landing of a Marine Landing Force and supporting forces by helicopters and tilt rotors supported by Joint Strike Fighters (JSF) F-35B. LHA(R) Flight 0 is considered a transitional increment intended to increase the aviation capabilities of Amphibious Assault Class Ships. LHA(R) Flight 0 consisted of two ships - LHA 6 and LHA 7. LHA(R) Flight 1 is the second increment in the LHA 6 Class, with LHA 8 (FY 2017) being the first ship of Flight 1. The LHA(R) Flight 1 design continues the incremental development of Amphibious Assault Class Ships by adding a well deck and increasing the flight deck capacity by reducing the footprint of the island and adding a sponson. The Flight 1 ships maintain an aviation centric capability with the addition of a well deck that will accommodate two Landing Craft, Air Cushion (LCAC) vehicles. LHA 9 (FY 2023) is the second LHA(R) Flight 1 ship and assumes a LHA 8 baseline design.
A42: SCN | B42: Procurement | C42: 3050 | D42: Medium Landing Ship | E42: 1 | F42: Full ship DD&C | G42: Medium Landing Ship (LSM) is a medium-sized landing ship that enables distributed maneuver and logistics such as Distributed Maritime Operations (DMO), Littoral Operations in a Contested Environment (LOCE), and Expeditionary Advanced Base Operations (EABO), in support of the Marine Littoral | J42: 29668 | L42: 0 | M42: 1963941 | N42: 1963941 | P42: 1963941 | Q42: 800000 | R42: 2763941 | T42: 1887500 | U42: 1887500 | X42: USN | Y42: Combatant Ships | Z42: Expeditionary & Seabasing Ships | AA42: LSM | AB42: P-40 Exhibit > LI 3050 > Medium Landing Ship | AC42: 353 | AF42: 3050 | AI42: Maritime Platforms & Systems | AJ42: Amphibious Ships | AK42: Medium Landing Ship (LSM) is a medium-sized landing ship that enables distributed maneuver and logistics such as Distributed Maritime Operations (DMO), Littoral Operations in a Contested Environment (LOCE), and Expeditionary Advanced Base Operations (EABO), in support of the Marine Littoral Regiment (MLR). It is designed to fill the gap in capability between the Navy's large, multipurpose amphibious warfare class ships and smaller landing vessels. This ship will deploy tailored logistics, select power projection and support strike capabilities via the embarked MLR. With the authorities granted in Section 128 of the FY 2025 National Defense Authorization Act, the LSM program will procure an existing design to construct Non-Developmental Vessels (NDV). This procurement is known as LSM Block 1. For the LSM Program, the Department requests a total of $1,963,941 thousand and a total quantity of nine. This request includes $0 thousand of discretionary and $1,963,941 thousand of mandatory (reconciliation) for a total of $1,963,941 thousand. The mandatory funds will be used to procure 9 ships. Further information for this reconciliation request is provided in Section 20002 (Shipbuilding) of the Reconciliation Exhibit.
A43: SCN | B43: Procurement | C43: 3039 | D43: Expeditionary Sea Base (ESB) | E43: 1 | F43: Full ship DD&C | G43: The Expeditionary Mobile Base (ESB) (formerly MLP Afloat Forward Staging Base (AFSB)) will serve as a dedicated Naval Afloat Forward Staging Base, optimized to support naval assets in a variety of missions rather than independently modifying ships-of-opportunity as required to meet these roles. The | I43: 0 | J43: 0 | L43: 0 | M43: 0 | N43: 0 | V43: [REFERENCE] | W43: CTC captured in 5300 / Completion of PY Shipbuilding Programs (ESB sub-item) | X43: MSC | Y43: Combatant Ships | Z43: Expeditionary & Seabasing Ships | AA43: T-ESB | AB43: P-40 Exhibit > LI 3039 > Expeditionary Sea Base | AC43: 357
A44: SCN | B44: Procurement | C44: 3043 | D44: Expeditionary Fast Transport (EPF) | E44: 1 | F44: Full ship DD&C | G44: Future joint forces will be responsive, deployable, agile, versatile, lethal, survivable, and sustainable. The nation will need lift assets that can provide for assured access, decrease predictability and dwell time, and have the capacity to quickly deliver troops and equipment together in a manner | I44: 0 | J44: 0 | L44: 0 | M44: 0 | N44: 0 | V44: [REFERENCE] | W44: CTC captured in 5300 / Completion of PY Shipbuilding Programs (JHSV sub-item) | X44: MSC | Y44: Combatant Ships | Z44: Expeditionary & Seabasing Ships | AA44: T-EPF | AB44: P-40 Exhibit > LI 3043 > Expeditionary Fast Transport | AC44: 361
A45: SCN | B45: Procurement | C45: 5025 | D45: TAO Fleet Oiler | E45: 1 | F45: Full ship DD&C | G45: For the T-AO 205 Program, the Department requests a total of $1,861,705 thousand and two ships. This request includes $8,346 thousand of discretionary and $1,853,359 thousand of mandatory (reconciliation) for a total of $1,861,705 thousand. The mandatory and discretionary funds support the contract | I45: 938315 | J45: 227154 | L45: 8346 | M45: 1853359 | N45: 1861705 | P45: 1853359 | Q45: 8346 | R45: 1861705 | S45: 1946063 | T45: 282820 | U45: 2228883 | V45: [PARENT] | X45: MSC | Y45: Combatant Ships | Z45: Combat Logistics Ships | AA45: T-AO | AB45: P-40 Exhibit > LI 5025 > TAO Fleet Oiler | AC45: 365 | AF45: 5025 | AI45: Maritime Platforms & Systems | AJ45: Combat Logistics Ships | AK45: For the T-AO 205 Program, the Department requests a total of $1,861,705 thousand and two ships. This request includes $8,346 thousand of discretionary and $1,853,359 thousand of mandatory (reconciliation) for a total of $1,861,705 thousand. The mandatory and discretionary funds support the contract award of 2 T-AO Fleet Oilers. Further information for this reconciliation request is provided in Section 20002 (Shipbuilding) of the Reconciliation Exhibit. The T-AO 205 John Lewis Fleet Oiler Class will recapitalize the existing T-AO 187 fleet oiler class. The Navy's Combat Logistics Force (CLF) oilers supply fuel and dry cargo to Navy ships at sea. The T-AO 205 Class will operate as shuttle ships from resupply posts to customer ships. Additionally, in conjunction with a dry cargo and ammunition ship (T-AKE), they will accompany and stay on-station with a Carrier Strike Group (CSG) to provide fuel as required to customer ships.
A46: SCN | B46: Procurement | D46: TAO Fleet Oiler - Net Procurement | E46: 1 | F46: Full ship DD&C | I46: 815420 | J46: 0 | L46: 8346 | M46: 1853359 | N46: 1861705 | V46: [SUB] | W46: 5025 / TAO Fleet Oiler | X46: MSC | Y46: Combatant Ships | Z46: Combat Logistics Ships | AA46: T-AO | AB46: P-1 Exhibit > BA 05 > Line 31 Net | AC46: 19 | AF46: 5025 | AI46: Maritime Platforms & Systems | AJ46: Combat Logistics Ships | AK46: For the T-AO 205 Program, the Department requests a total of $1,861,705 thousand and two ships. This request includes $8,346 thousand of discretionary and $1,853,359 thousand of mandatory (reconciliation) for a total of $1,861,705 thousand. The mandatory and discretionary funds support the contract award of 2 T-AO Fleet Oilers. Further information for this reconciliation request is provided in Section 20002 (Shipbuilding) of the Reconciliation Exhibit. The T-AO 205 John Lewis Fleet Oiler Class will recapitalize the existing T-AO 187 fleet oiler class. The Navy's Combat Logistics Force (CLF) oilers supply fuel and dry cargo to Navy ships at sea. The T-AO 205 Class will operate as shuttle ships from resupply posts to customer ships. Additionally, in conjunction with a dry cargo and ammunition ship (T-AKE), they will accompany and stay on-station with a Carrier Strike Group (CSG) to provide fuel as required to customer ships.
A47: SCN | B47: Procurement | D47: TAO Fleet Oiler - Completion PY (FY19-23) | E47: 1 | F47: Full ship DD&C | I47: 122895 | J47: 227154 | V47: [SUB] | W47: 5025 / TAO Fleet Oiler | X47: MSC | Y47: Combatant Ships | Z47: Combat Logistics Ships | AA47: T-AO | AB47: P-1 Exhibit > BA 05 > Line 31 CTC | AC47: 19 | AF47: 5025 | AI47: Maritime Platforms & Systems | AJ47: Combat Logistics Ships | AK47: For the T-AO 205 Program, the Department requests a total of $1,861,705 thousand and two ships. This request includes $8,346 thousand of discretionary and $1,853,359 thousand of mandatory (reconciliation) for a total of $1,861,705 thousand. The mandatory and discretionary funds support the contract award of 2 T-AO Fleet Oilers. Further information for this reconciliation request is provided in Section 20002 (Shipbuilding) of the Reconciliation Exhibit. The T-AO 205 John Lewis Fleet Oiler Class will recapitalize the existing T-AO 187 fleet oiler class. The Navy's Combat Logistics Force (CLF) oilers supply fuel and dry cargo to Navy ships at sea. The T-AO 205 Class will operate as shuttle ships from resupply posts to customer ships. Additionally, in conjunction with a dry cargo and ammunition ship (T-AKE), they will accompany and stay on-station with a Carrier Strike Group (CSG) to provide fuel as required to customer ships.
A48: SCN | B48: Procurement | C48: 5030 | D48: TAGOS Surtass Ships | E48: 1 | F48: Full ship DD&C | G48: Auxiliary General Ocean Surveillance (T-AGOS) ships gather underwater acoustical data to support the mission of the Integrated Undersea Surveillance System (IUSS) by providing a ship platform capable of theater anti-submarine acoustic passive and active surveillance. T-AGOS ships are operated by | I48: 513466 | J48: 0 | L48: 612205 | M48: 0 | N48: 612205 | Q48: 612205 | R48: 612205 | S48: 610664 | T48: 100000 | U48: 710664 | V48: [PARENT] | X48: MSC | Y48: Combatant Ships | Z48: Surveillance Ships | AA48: T-AGOS | AB48: P-40 Exhibit > LI 5030 > TAGOS Surtass Ships | AC48: 373 | AF48: 5030 | AI48: Maritime Platforms & Systems | AJ48: Auxiliary & Support Ships | AK48: Auxiliary General Ocean Surveillance (T-AGOS) ships gather underwater acoustical data to support the mission of the Integrated Undersea Surveillance System (IUSS) by providing a ship platform capable of theater anti-submarine acoustic passive and active surveillance. T-AGOS ships are operated by Military Sealift Command to support the anti-submarine warfare mission of the commanders of the Atlantic and Pacific Fleets. The two current classes of surveillance ships use Surveillance Towed-Array Sensor System (SURTASS) equipment to gather undersea acoustic data. The ships also carry electronic equipment to process and transmit that data via satellite to shore stations for evaluation. Funding will support recapitalization of the four Small Waterplane Area Twin Hull (SWATH) T-19 Class and one SWATH T-23 Class ships.
A49: SCN | B49: Procurement | D49: TAGOS - SFF for FY 2022 | E49: 1 | F49: Full ship DD&C | I49: 513466 | V49: [SUB] | W49: 5030 / TAGOS Surtass Ships | X49: MSC | Y49: Combatant Ships | Z49: Surveillance Ships | AA49: T-AGOS | AB49: P-1 Exhibit > BA 05 > Line 34 SFF | AC49: 19 | AF49: 5030 | AI49: Maritime Platforms & Systems | AJ49: Auxiliary & Support Ships | AK49: Auxiliary General Ocean Surveillance (T-AGOS) ships gather underwater acoustical data to support the mission of the Integrated Undersea Surveillance System (IUSS) by providing a ship platform capable of theater anti-submarine acoustic passive and active surveillance. T-AGOS ships are operated by Military Sealift Command to support the anti-submarine warfare mission of the commanders of the Atlantic and Pacific Fleets. The two current classes of surveillance ships use Surveillance Towed-Array Sensor System (SURTASS) equipment to gather undersea acoustic data. The ships also carry electronic equipment to process and transmit that data via satellite to shore stations for evaluation. Funding will support recapitalization of the four Small Waterplane Area Twin Hull (SWATH) T-19 Class and one SWATH T-23 Class ships.
A50: SCN | B50: Procurement | D50: TAGOS - Net Procurement FY 2026 | E50: 1 | F50: Full ship DD&C | L50: 612205 | N50: 612205 | V50: [SUB] | W50: 5030 / TAGOS Surtass Ships | X50: MSC | Y50: Combatant Ships | Z50: Surveillance Ships | AA50: T-AGOS | AB50: P-1 Exhibit > BA 05 > Line 34 Net | AC50: 20 | AF50: 5030 | AI50: Maritime Platforms & Systems | AJ50: Auxiliary & Support Ships | AK50: Auxiliary General Ocean Surveillance (T-AGOS) ships gather underwater acoustical data to support the mission of the Integrated Undersea Surveillance System (IUSS) by providing a ship platform capable of theater anti-submarine acoustic passive and active surveillance. T-AGOS ships are operated by Military Sealift Command to support the anti-submarine warfare mission of the commanders of the Atlantic and Pacific Fleets. The two current classes of surveillance ships use Surveillance Towed-Array Sensor System (SURTASS) equipment to gather undersea acoustic data. The ships also carry electronic equipment to process and transmit that data via satellite to shore stations for evaluation. Funding will support recapitalization of the four Small Waterplane Area Twin Hull (SWATH) T-19 Class and one SWATH T-23 Class ships.
A51: SCN | B51: Procurement | C51: 5035 | D51: Towing Salvage and Rescue Ship (ATS) | E51: 1 | F51: Full ship DD&C | G51: The Navy requires ocean-going towing, salvage, and rescue capabilities to support Fleet operations. The Navy's current capabilities are provided by four Fleet Ocean Tugs (T-ATF) 166 Class Fleet tugs and four Rescue and Salvage Ships (T-ARS 50) Class salvage ships which will reach the end of their | I51: 22959 | J51: 82587 | L51: 0 | M51: 0 | N51: 0 | Q51: 141500 | R51: 141500 | X51: MSC | Y51: Combatant Ships | Z51: Salvage Ships & Fleet Ocean Tugs | AA51: T-ATS | AB51: P-40 Exhibit > LI 5035 > Towing Salvage and Rescue Ship | AC51: 381 | AF51: 5035 | AI51: Maritime Platforms & Systems | AJ51: Auxiliary & Support Ships | AK51: The Navy requires ocean-going towing, salvage, and rescue capabilities to support Fleet operations. The Navy's current capabilities are provided by four Fleet Ocean Tugs (T-ATF) 166 Class Fleet tugs and four Rescue and Salvage Ships (T-ARS 50) Class salvage ships which will reach the end of their expected service lives beginning in 2020 and 2025, respectively. The Towing, Salvage and Rescue Ships (T-ATS 6 Navajo Class) will recapitalize the current Fleet tugs and salvage ships with a common hull that is capable of performing the missions of the retiring T-ATF and T-ARS classes.
A52: SCN | B52: Procurement | C52: 5087 | D52: Oceanographic Ships | E52: 1 | F52: Full ship DD&C | G52: The FY 2018 Omnibus Appropriations Act included a Congressional add for Detail Design and Construction (DD&C) efforts for one T-AGS 60 vessel. T-AGS 67 is a repeat platform of T-AGS 66 and includes the Moon Pool Launch and Recovery System. The TAGS 67 will be capable of deep ocean and coastal surveys, oceanographic sampling and data collections. | I52: 0 | J52: 18000 | L52: 0 | M52: 0 | N52: 0 | X52: MSC | Y52: Auxiliary Ships | Z52: Research, Survey & Instrumentation Ships | AA52: T-AGS | AB52: P-40 Exhibit > LI 5087 > Oceanographic Ships | AC52: 385 | AF52: 5087 | AI52: Maritime Platforms & Systems | AJ52: Auxiliary & Support Ships | AK52: The FY 2018 Omnibus Appropriations Act included a Congressional add for Detail Design and Construction (DD&C) efforts for one T-AGS 60 vessel. T-AGS 67 is a repeat platform of T-AGS 66 and includes the Moon Pool Launch and Recovery System. The TAGS 67 will be capable of deep ocean and coastal surveys, oceanographic sampling and data collections of surface, midwater and ocean floor parameters, shipboard oceanographic data processing and sample analysis, and operation of remotely operated vehicles and hydrographic survey launches.
A53: SCN | B53: Procurement | C53: 5100 | D53: LCU 1700 | E53: 1 | F53: Full ship DD&C | G53: For the Landing Craft, Utility (LCU) 1700 program, the Department requests a total of $295,000 thousand and a total quantity of nine. This request includes $0 thousand of discretionary funding and $295,000 thousand of mandatory (reconciliation) funding. The mandatory funds support the contract | I53: 62532 | J53: 0 | L53: 0 | M53: 295000 | N53: 295000 | P53: 295000 | Q53: 0 | R53: 295000 | X53: USN | Y53: Combatant Crafts | Z53: Amphibious Warfare Craft | AA53: LCU | AB53: P-40 Exhibit > LI 5100 > LCU 1700 | AC53: 389 | AF53: 5100 | AI53: Maritime Platforms & Systems | AJ53: Auxiliary & Support Ships | AK53: For the Landing Craft, Utility (LCU) 1700 program, the Department requests a total of $295,000 thousand and a total quantity of nine. This request includes $0 thousand of discretionary funding and $295,000 thousand of mandatory (reconciliation) funding. The mandatory funds support the contract award of 9 LCU craft and development of a second shipyard. Further information for this reconciliation request is provided in Section 20002 (Shipbuilding) of the Reconciliation Exhibit. The LCU 1700 program provides heavy lift capability to transport personnel, weapons, equipment, and cargo from the ship to shore and shore to shore across the range of military operations (ROMO). LCU 1700 will be able to conduct 24 hours/day operations for up to 10 days for continuous landing of troops, equipment, and supplies; provide support for missions requiring persistence such as riverine sustainment, surveillance or port clearing; and execute missions to reinforce, reposition, and resupply forces over a wide operating area. LCU 1700 provides the functional replacement for the LCU 1610 class of landing craft, all of which have significantly exceeded their 25 year service life, the average age exceeds 50 years old. The initial Swiftships LLC contract was terminated for default in February 2024. No craft from the initial contract will be delivered. A Detail Design and Construction contract was awarded in September 2023 for three LCUs (LCU 1710-1712), with the option for LCUs 1713 and 1714 awarded in July 2024. There are options for up to seven additional craft to Austal USA.
A54: SCN | B54: Procurement | D54: Strategic Sealift | E54: 1 | F54: Full ship DD&C | M54: 600000 | N54: 600000 | S54: 450000 | U54: 450000 | X54: MSC | Y54: Auxiliary Ships | Z54: Cargo & Vehicle Cargo Ships | AA54: T-AK / T-AKR | AB54: P-1 Exhibit > BA 05 > Line 40 | AC54: 19
A55: SCN | B55: Procurement | C55: 5110 | D55: Outfitting | E55: 1 | F55: GFE / combat systems for newbuild | G55: Outfitting (OF) funds are used to acquire on board repair parts, other secondary items, equipage, recreation items, precommissioning crew support and general use consumables furnished to the shipbuilder or the fitting-out activity to fill the ship's initial allowances as defined by the baseline | I55: 512019 | J55: 585967 | L55: 863846 | M55: 23449 | N55: 887295 | P55: 0 | Q55: 886846 | R55: 886846 | S55: 741270 | U55: 741270 | V55: [PARENT] | AB55: P-40 Exhibit > LI 5110 > Outfitting | AC55: 395 | AF55: 5110 | AI55: Maritime Sustainment & Lifecycle Support | AJ55: Depot-Level Repair Parts | AK55: Outfitting (OF) funds are used to acquire on board repair parts, other secondary items, equipage, recreation items, precommissioning crew support and general use consumables furnished to the shipbuilder or the fitting-out activity to fill the ship's initial allowances as defined by the baseline coordinated shipboard allowance list (COSAL). The program also budgets for contractor-furnished spares, a lead-time away from delivery. The program ensures operational readiness of ships undergoing new construction, conversion, service life extension program (SLEP), and nuclear refueling. It ensures these ships receive their full allowances of spare parts and equipment which are vitally required to support the shipboard maintenance process; ensures ships are equipped with operating space items (tools, test equipment, damage control), personnel safety and survivability commodities for successful completion of builder sea trials; supports shipboard maintenance and thereby achieving the OPNAV-directed supply readiness goals for material on board ship at delivery. SCN funding for the initial fill of allowance list items are limited to those items on the COSAL and authorized requirements through the Obligation Work Limiting Date (OWLD). While most outfitting funds are executed prior to ships' completion of fitting out dates, some outfitting funding may be required in the fiscal year following the scheduled Delivery Date. Post Delivery (PD) funding covers the repair of government-responsible items which were believed to have been complete to standard and/or operable at delivery, as well as funding to conduct tests and trials after delivery. It is essential to deliver to the Fleet complete ships, free from both contractor and government responsible deficiencies, capable of supporting the Navy's mission. The Post Shakedown Availability (PSA) is a shipyard availability assigned to commence after delivery and to be completed prior to the expiration of the SCN OWLD. It is during this time that acceptance and final contract trials deficiencies will be corrected. The purpose of the PSA is to correct new construction deficiencies found during the shakedown period; to correct contractor and government responsible deficiencies previously authorized; and accomplishment of other improvements or class items as authorized. Funding is used for corrections authorized by the ship's Program Manager as a result of builders' trials (pre-delivery), acceptance or underway trials, final contract trials, trial board items, and correction of production-related defects or deficiencies which develop during the post delivery period. Although the majority of post delivery funding occurs after ships' delivery dates, some funding is required prior to the delivery date in preparation for post delivery events. First Destination Transportation (FDT). FDT delivers material from a procurement source to the first point of use or storage which may be in the Continental United States or overseas. The procurement source may be a supplier outside of the Department of Defense (DoD) supply system or a DoD activity which fabricates new material. FDT also includes transportation from point of origin to point of use or storage when Navy-owned material or equipment is provided to a contractor incident to a Research and Development project or a system/equipment acquisition or modification.
A56: SCN | B56: Procurement | C56: 5110 | D56: Outfitting - COLUMBIA Class | E56: 1 | F56: GFE / combat systems for newbuild | L56: 46987 | V56: [SUB] | W56: 5110 / Outfitting | X56: USN | Y56: Combatant Ships | Z56: Submarines | AA56: SSBN | AB56: P-40 > LI 5110 > P-29/P-30 > CO CLASS | AC56: 395 | AF56: 5110 | AI56: Maritime Sustainment & Lifecycle Support | AJ56: Depot-Level Repair Parts | AK56: Outfitting (OF) funds are used to acquire on board repair parts, other secondary items, equipage, recreation items, precommissioning crew support and general use consumables furnished to the shipbuilder or the fitting-out activity to fill the ship's initial allowances as defined by the baseline coordinated shipboard allowance list (COSAL). The program also budgets for contractor-furnished spares, a lead-time away from delivery. The program ensures operational readiness of ships undergoing new construction, conversion, service life extension program (SLEP), and nuclear refueling. It ensures these ships receive their full allowances of spare parts and equipment which are vitally required to support the shipboard maintenance process; ensures ships are equipped with operating space items (tools, test equipment, damage control), personnel safety and survivability commodities for successful completion of builder sea trials; supports shipboard maintenance and thereby achieving the OPNAV-directed supply readiness goals for material on board ship at delivery. SCN funding for the initial fill of allowance list items are limited to those items on the COSAL and authorized requirements through the Obligation Work Limiting Date (OWLD). While most outfitting funds are executed prior to ships' completion of fitting out dates, some outfitting funding may be required in the fiscal year following the scheduled Delivery Date. Post Delivery (PD) funding covers the repair of government-responsible items which were believed to have been complete to standard and/or operable at delivery, as well as funding to conduct tests and trials after delivery. It is essential to deliver to the Fleet complete ships, free from both contractor and government responsible deficiencies, capable of supporting the Navy's mission. The Post Shakedown Availability (PSA) is a shipyard availability assigned to commence after delivery and to be completed prior to the expiration of the SCN OWLD. It is during this time that acceptance and final contract trials deficiencies will be corrected. The purpose of the PSA is to correct new construction deficiencies found during the shakedown period; to correct contractor and government responsible deficiencies previously authorized; and accomplishment of other improvements or class items as authorized. Funding is used for corrections authorized by the ship's Program Manager as a result of builders' trials (pre-delivery), acceptance or underway trials, final contract trials, trial board items, and correction of production-related defects or deficiencies which develop during the post delivery period. Although the majority of post delivery funding occurs after ships' delivery dates, some funding is required prior to the delivery date in preparation for post delivery events. First Destination Transportation (FDT). FDT delivers material from a procurement source to the first point of use or storage which may be in the Continental United States or overseas. The procurement source may be a supplier outside of the Department of Defense (DoD) supply system or a DoD activity which fabricates new material. FDT also includes transportation from point of origin to point of use or storage when Navy-owned material or equipment is provided to a contractor incident to a Research and Development project or a system/equipment acquisition or modification.
A57: SCN | B57: Procurement | C57: 5110 | D57: Outfitting - CVN (79/80) | E57: 1 | F57: GFE / combat systems for newbuild | L57: 78780 | V57: [SUB] | W57: 5110 / Outfitting | X57: USN | Y57: Combatant Ships | Z57: Aircraft Carriers | AA57: CVN | AB57: P-40 > LI 5110 > P-29/P-30 > CVN | AC57: 395 | AF57: 5110 | AI57: Maritime Sustainment & Lifecycle Support | AJ57: Depot-Level Repair Parts | AK57: Outfitting (OF) funds are used to acquire on board repair parts, other secondary items, equipage, recreation items, precommissioning crew support and general use consumables furnished to the shipbuilder or the fitting-out activity to fill the ship's initial allowances as defined by the baseline coordinated shipboard allowance list (COSAL). The program also budgets for contractor-furnished spares, a lead-time away from delivery. The program ensures operational readiness of ships undergoing new construction, conversion, service life extension program (SLEP), and nuclear refueling. It ensures these ships receive their full allowances of spare parts and equipment which are vitally required to support the shipboard maintenance process; ensures ships are equipped with operating space items (tools, test equipment, damage control), personnel safety and survivability commodities for successful completion of builder sea trials; supports shipboard maintenance and thereby achieving the OPNAV-directed supply readiness goals for material on board ship at delivery. SCN funding for the initial fill of allowance list items are limited to those items on the COSAL and authorized requirements through the Obligation Work Limiting Date (OWLD). While most outfitting funds are executed prior to ships' completion of fitting out dates, some outfitting funding may be required in the fiscal year following the scheduled Delivery Date. Post Delivery (PD) funding covers the repair of government-responsible items which were believed to have been complete to standard and/or operable at delivery, as well as funding to conduct tests and trials after delivery. It is essential to deliver to the Fleet complete ships, free from both contractor and government responsible deficiencies, capable of supporting the Navy's mission. The Post Shakedown Availability (PSA) is a shipyard availability assigned to commence after delivery and to be completed prior to the expiration of the SCN OWLD. It is during this time that acceptance and final contract trials deficiencies will be corrected. The purpose of the PSA is to correct new construction deficiencies found during the shakedown period; to correct contractor and government responsible deficiencies previously authorized; and accomplishment of other improvements or class items as authorized. Funding is used for corrections authorized by the ship's Program Manager as a result of builders' trials (pre-delivery), acceptance or underway trials, final contract trials, trial board items, and correction of production-related defects or deficiencies which develop during the post delivery period. Although the majority of post delivery funding occurs after ships' delivery dates, some funding is required prior to the delivery date in preparation for post delivery events. First Destination Transportation (FDT). FDT delivers material from a procurement source to the first point of use or storage which may be in the Continental United States or overseas. The procurement source may be a supplier outside of the Department of Defense (DoD) supply system or a DoD activity which fabricates new material. FDT also includes transportation from point of origin to point of use or storage when Navy-owned material or equipment is provided to a contractor incident to a Research and Development project or a system/equipment acquisition or modification.
A58: SCN | B58: Procurement | C58: 5110 | D58: Outfitting - Virginia Class | E58: 1 | F58: GFE / combat systems for newbuild | L58: 218616 | V58: [SUB] | W58: 5110 / Outfitting | X58: USN | Y58: Combatant Ships | Z58: Submarines | AA58: SSN | AB58: P-40 > LI 5110 > P-29/P-30 > VIRGINIA | AC58: 395 | AF58: 5110 | AI58: Maritime Sustainment & Lifecycle Support | AJ58: Depot-Level Repair Parts | AK58: Outfitting (OF) funds are used to acquire on board repair parts, other secondary items, equipage, recreation items, precommissioning crew support and general use consumables furnished to the shipbuilder or the fitting-out activity to fill the ship's initial allowances as defined by the baseline coordinated shipboard allowance list (COSAL). The program also budgets for contractor-furnished spares, a lead-time away from delivery. The program ensures operational readiness of ships undergoing new construction, conversion, service life extension program (SLEP), and nuclear refueling. It ensures these ships receive their full allowances of spare parts and equipment which are vitally required to support the shipboard maintenance process; ensures ships are equipped with operating space items (tools, test equipment, damage control), personnel safety and survivability commodities for successful completion of builder sea trials; supports shipboard maintenance and thereby achieving the OPNAV-directed supply readiness goals for material on board ship at delivery. SCN funding for the initial fill of allowance list items are limited to those items on the COSAL and authorized requirements through the Obligation Work Limiting Date (OWLD). While most outfitting funds are executed prior to ships' completion of fitting out dates, some outfitting funding may be required in the fiscal year following the scheduled Delivery Date. Post Delivery (PD) funding covers the repair of government-responsible items which were believed to have been complete to standard and/or operable at delivery, as well as funding to conduct tests and trials after delivery. It is essential to deliver to the Fleet complete ships, free from both contractor and government responsible deficiencies, capable of supporting the Navy's mission. The Post Shakedown Availability (PSA) is a shipyard availability assigned to commence after delivery and to be completed prior to the expiration of the SCN OWLD. It is during this time that acceptance and final contract trials deficiencies will be corrected. The purpose of the PSA is to correct new construction deficiencies found during the shakedown period; to correct contractor and government responsible deficiencies previously authorized; and accomplishment of other improvements or class items as authorized. Funding is used for corrections authorized by the ship's Program Manager as a result of builders' trials (pre-delivery), acceptance or underway trials, final contract trials, trial board items, and correction of production-related defects or deficiencies which develop during the post delivery period. Although the majority of post delivery funding occurs after ships' delivery dates, some funding is required prior to the delivery date in preparation for post delivery events. First Destination Transportation (FDT). FDT delivers material from a procurement source to the first point of use or storage which may be in the Continental United States or overseas. The procurement source may be a supplier outside of the Department of Defense (DoD) supply system or a DoD activity which fabricates new material. FDT also includes transportation from point of origin to point of use or storage when Navy-owned material or equipment is provided to a contractor incident to a Research and Development project or a system/equipment acquisition or modification.
A59: SCN | B59: Procurement | C59: 5110 | D59: Outfitting - CVN RCOH | E59: 5 | F59: RCOH | L59: 12200 | V59: [SUB] | W59: 5110 / Outfitting | X59: USN | Y59: Combatant Ships | Z59: Aircraft Carriers | AA59: CVN | AB59: P-40 > LI 5110 > P-29/P-30 > CVN-RCOH | AC59: 395 | AF59: 5110 | AI59: Maritime Sustainment & Lifecycle Support | AJ59: Depot-Level Repair Parts | AK59: Outfitting (OF) funds are used to acquire on board repair parts, other secondary items, equipage, recreation items, precommissioning crew support and general use consumables furnished to the shipbuilder or the fitting-out activity to fill the ship's initial allowances as defined by the baseline coordinated shipboard allowance list (COSAL). The program also budgets for contractor-furnished spares, a lead-time away from delivery. The program ensures operational readiness of ships undergoing new construction, conversion, service life extension program (SLEP), and nuclear refueling. It ensures these ships receive their full allowances of spare parts and equipment which are vitally required to support the shipboard maintenance process; ensures ships are equipped with operating space items (tools, test equipment, damage control), personnel safety and survivability commodities for successful completion of builder sea trials; supports shipboard maintenance and thereby achieving the OPNAV-directed supply readiness goals for material on board ship at delivery. SCN funding for the initial fill of allowance list items are limited to those items on the COSAL and authorized requirements through the Obligation Work Limiting Date (OWLD). While most outfitting funds are executed prior to ships' completion of fitting out dates, some outfitting funding may be required in the fiscal year following the scheduled Delivery Date. Post Delivery (PD) funding covers the repair of government-responsible items which were believed to have been complete to standard and/or operable at delivery, as well as funding to conduct tests and trials after delivery. It is essential to deliver to the Fleet complete ships, free from both contractor and government responsible deficiencies, capable of supporting the Navy's mission. The Post Shakedown Availability (PSA) is a shipyard availability assigned to commence after delivery and to be completed prior to the expiration of the SCN OWLD. It is during this time that acceptance and final contract trials deficiencies will be corrected. The purpose of the PSA is to correct new construction deficiencies found during the shakedown period; to correct contractor and government responsible deficiencies previously authorized; and accomplishment of other improvements or class items as authorized. Funding is used for corrections authorized by the ship's Program Manager as a result of builders' trials (pre-delivery), acceptance or underway trials, final contract trials, trial board items, and correction of production-related defects or deficiencies which develop during the post delivery period. Although the majority of post delivery funding occurs after ships' delivery dates, some funding is required prior to the delivery date in preparation for post delivery events. First Destination Transportation (FDT). FDT delivers material from a procurement source to the first point of use or storage which may be in the Continental United States or overseas. The procurement source may be a supplier outside of the Department of Defense (DoD) supply system or a DoD activity which fabricates new material. FDT also includes transportation from point of origin to point of use or storage when Navy-owned material or equipment is provided to a contractor incident to a Research and Development project or a system/equipment acquisition or modification.
A60: SCN | B60: Procurement | C60: 5110 | D60: Outfitting - DDG 1000 | E60: 1 | F60: GFE / combat systems for newbuild | L60: 9 | V60: [SUB] | W60: 5110 / Outfitting | X60: USN | Y60: Combatant Ships | Z60: Surface Combatants | AA60: DDG | AB60: P-40 > LI 5110 > P-29/P-30 > DDG 1000 | AC60: 395 | AF60: 5110 | AI60: Maritime Sustainment & Lifecycle Support | AJ60: Depot-Level Repair Parts | AK60: Outfitting (OF) funds are used to acquire on board repair parts, other secondary items, equipage, recreation items, precommissioning crew support and general use consumables furnished to the shipbuilder or the fitting-out activity to fill the ship's initial allowances as defined by the baseline coordinated shipboard allowance list (COSAL). The program also budgets for contractor-furnished spares, a lead-time away from delivery. The program ensures operational readiness of ships undergoing new construction, conversion, service life extension program (SLEP), and nuclear refueling. It ensures these ships receive their full allowances of spare parts and equipment which are vitally required to support the shipboard maintenance process; ensures ships are equipped with operating space items (tools, test equipment, damage control), personnel safety and survivability commodities for successful completion of builder sea trials; supports shipboard maintenance and thereby achieving the OPNAV-directed supply readiness goals for material on board ship at delivery. SCN funding for the initial fill of allowance list items are limited to those items on the COSAL and authorized requirements through the Obligation Work Limiting Date (OWLD). While most outfitting funds are executed prior to ships' completion of fitting out dates, some outfitting funding may be required in the fiscal year following the scheduled Delivery Date. Post Delivery (PD) funding covers the repair of government-responsible items which were believed to have been complete to standard and/or operable at delivery, as well as funding to conduct tests and trials after delivery. It is essential to deliver to the Fleet complete ships, free from both contractor and government responsible deficiencies, capable of supporting the Navy's mission. The Post Shakedown Availability (PSA) is a shipyard availability assigned to commence after delivery and to be completed prior to the expiration of the SCN OWLD. It is during this time that acceptance and final contract trials deficiencies will be corrected. The purpose of the PSA is to correct new construction deficiencies found during the shakedown period; to correct contractor and government responsible deficiencies previously authorized; and accomplishment of other improvements or class items as authorized. Funding is used for corrections authorized by the ship's Program Manager as a result of builders' trials (pre-delivery), acceptance or underway trials, final contract trials, trial board items, and correction of production-related defects or deficiencies which develop during the post delivery period. Although the majority of post delivery funding occurs after ships' delivery dates, some funding is required prior to the delivery date in preparation for post delivery events. First Destination Transportation (FDT). FDT delivers material from a procurement source to the first point of use or storage which may be in the Continental United States or overseas. The procurement source may be a supplier outside of the Department of Defense (DoD) supply system or a DoD activity which fabricates new material. FDT also includes transportation from point of origin to point of use or storage when Navy-owned material or equipment is provided to a contractor incident to a Research and Development project or a system/equipment acquisition or modification.
A61: SCN | B61: Procurement | C61: 5110 | D61: Outfitting - DDG-51 | E61: 1 | F61: GFE / combat systems for newbuild | L61: 167272 | V61: [SUB] | W61: 5110 / Outfitting | X61: USN | Y61: Combatant Ships | Z61: Surface Combatants | AA61: DDG | AB61: P-40 > LI 5110 > P-29/P-30 > DDG | AC61: 395 | AF61: 5110 | AI61: Maritime Sustainment & Lifecycle Support | AJ61: Depot-Level Repair Parts | AK61: Outfitting (OF) funds are used to acquire on board repair parts, other secondary items, equipage, recreation items, precommissioning crew support and general use consumables furnished to the shipbuilder or the fitting-out activity to fill the ship's initial allowances as defined by the baseline coordinated shipboard allowance list (COSAL). The program also budgets for contractor-furnished spares, a lead-time away from delivery. The program ensures operational readiness of ships undergoing new construction, conversion, service life extension program (SLEP), and nuclear refueling. It ensures these ships receive their full allowances of spare parts and equipment which are vitally required to support the shipboard maintenance process; ensures ships are equipped with operating space items (tools, test equipment, damage control), personnel safety and survivability commodities for successful completion of builder sea trials; supports shipboard maintenance and thereby achieving the OPNAV-directed supply readiness goals for material on board ship at delivery. SCN funding for the initial fill of allowance list items are limited to those items on the COSAL and authorized requirements through the Obligation Work Limiting Date (OWLD). While most outfitting funds are executed prior to ships' completion of fitting out dates, some outfitting funding may be required in the fiscal year following the scheduled Delivery Date. Post Delivery (PD) funding covers the repair of government-responsible items which were believed to have been complete to standard and/or operable at delivery, as well as funding to conduct tests and trials after delivery. It is essential to deliver to the Fleet complete ships, free from both contractor and government responsible deficiencies, capable of supporting the Navy's mission. The Post Shakedown Availability (PSA) is a shipyard availability assigned to commence after delivery and to be completed prior to the expiration of the SCN OWLD. It is during this time that acceptance and final contract trials deficiencies will be corrected. The purpose of the PSA is to correct new construction deficiencies found during the shakedown period; to correct contractor and government responsible deficiencies previously authorized; and accomplishment of other improvements or class items as authorized. Funding is used for corrections authorized by the ship's Program Manager as a result of builders' trials (pre-delivery), acceptance or underway trials, final contract trials, trial board items, and correction of production-related defects or deficiencies which develop during the post delivery period. Although the majority of post delivery funding occurs after ships' delivery dates, some funding is required prior to the delivery date in preparation for post delivery events. First Destination Transportation (FDT). FDT delivers material from a procurement source to the first point of use or storage which may be in the Continental United States or overseas. The procurement source may be a supplier outside of the Department of Defense (DoD) supply system or a DoD activity which fabricates new material. FDT also includes transportation from point of origin to point of use or storage when Navy-owned material or equipment is provided to a contractor incident to a Research and Development project or a system/equipment acquisition or modification.
A62: SCN | B62: Procurement | C62: 5110 | D62: Outfitting - LCS | E62: 1 | F62: GFE / combat systems for newbuild | L62: 89186 | V62: [SUB] | W62: 5110 / Outfitting | X62: USN | Y62: Combatant Ships | Z62: Surface Combatants | AA62: LCS | AB62: P-40 > LI 5110 > P-29/P-30 > LCS | AC62: 395 | AF62: 5110 | AI62: Maritime Sustainment & Lifecycle Support | AJ62: Depot-Level Repair Parts | AK62: Outfitting (OF) funds are used to acquire on board repair parts, other secondary items, equipage, recreation items, precommissioning crew support and general use consumables furnished to the shipbuilder or the fitting-out activity to fill the ship's initial allowances as defined by the baseline coordinated shipboard allowance list (COSAL). The program also budgets for contractor-furnished spares, a lead-time away from delivery. The program ensures operational readiness of ships undergoing new construction, conversion, service life extension program (SLEP), and nuclear refueling. It ensures these ships receive their full allowances of spare parts and equipment which are vitally required to support the shipboard maintenance process; ensures ships are equipped with operating space items (tools, test equipment, damage control), personnel safety and survivability commodities for successful completion of builder sea trials; supports shipboard maintenance and thereby achieving the OPNAV-directed supply readiness goals for material on board ship at delivery. SCN funding for the initial fill of allowance list items are limited to those items on the COSAL and authorized requirements through the Obligation Work Limiting Date (OWLD). While most outfitting funds are executed prior to ships' completion of fitting out dates, some outfitting funding may be required in the fiscal year following the scheduled Delivery Date. Post Delivery (PD) funding covers the repair of government-responsible items which were believed to have been complete to standard and/or operable at delivery, as well as funding to conduct tests and trials after delivery. It is essential to deliver to the Fleet complete ships, free from both contractor and government responsible deficiencies, capable of supporting the Navy's mission. The Post Shakedown Availability (PSA) is a shipyard availability assigned to commence after delivery and to be completed prior to the expiration of the SCN OWLD. It is during this time that acceptance and final contract trials deficiencies will be corrected. The purpose of the PSA is to correct new construction deficiencies found during the shakedown period; to correct contractor and government responsible deficiencies previously authorized; and accomplishment of other improvements or class items as authorized. Funding is used for corrections authorized by the ship's Program Manager as a result of builders' trials (pre-delivery), acceptance or underway trials, final contract trials, trial board items, and correction of production-related defects or deficiencies which develop during the post delivery period. Although the majority of post delivery funding occurs after ships' delivery dates, some funding is required prior to the delivery date in preparation for post delivery events. First Destination Transportation (FDT). FDT delivers material from a procurement source to the first point of use or storage which may be in the Continental United States or overseas. The procurement source may be a supplier outside of the Department of Defense (DoD) supply system or a DoD activity which fabricates new material. FDT also includes transportation from point of origin to point of use or storage when Navy-owned material or equipment is provided to a contractor incident to a Research and Development project or a system/equipment acquisition or modification.
A63: SCN | B63: Procurement | C63: 5110 | D63: Outfitting - LPD Flight II | E63: 1 | F63: GFE / combat systems for newbuild | L63: 49090 | V63: [SUB] | W63: 5110 / Outfitting | X63: USN | Y63: Combatant Ships | Z63: Amphibious Warfare Ships | AA63: LPD | AB63: P-40 > LI 5110 > P-29/P-30 > LPD FLT II | AC63: 395 | AF63: 5110 | AI63: Maritime Sustainment & Lifecycle Support | AJ63: Depot-Level Repair Parts | AK63: Outfitting (OF) funds are used to acquire on board repair parts, other secondary items, equipage, recreation items, precommissioning crew support and general use consumables furnished to the shipbuilder or the fitting-out activity to fill the ship's initial allowances as defined by the baseline coordinated shipboard allowance list (COSAL). The program also budgets for contractor-furnished spares, a lead-time away from delivery. The program ensures operational readiness of ships undergoing new construction, conversion, service life extension program (SLEP), and nuclear refueling. It ensures these ships receive their full allowances of spare parts and equipment which are vitally required to support the shipboard maintenance process; ensures ships are equipped with operating space items (tools, test equipment, damage control), personnel safety and survivability commodities for successful completion of builder sea trials; supports shipboard maintenance and thereby achieving the OPNAV-directed supply readiness goals for material on board ship at delivery. SCN funding for the initial fill of allowance list items are limited to those items on the COSAL and authorized requirements through the Obligation Work Limiting Date (OWLD). While most outfitting funds are executed prior to ships' completion of fitting out dates, some outfitting funding may be required in the fiscal year following the scheduled Delivery Date. Post Delivery (PD) funding covers the repair of government-responsible items which were believed to have been complete to standard and/or operable at delivery, as well as funding to conduct tests and trials after delivery. It is essential to deliver to the Fleet complete ships, free from both contractor and government responsible deficiencies, capable of supporting the Navy's mission. The Post Shakedown Availability (PSA) is a shipyard availability assigned to commence after delivery and to be completed prior to the expiration of the SCN OWLD. It is during this time that acceptance and final contract trials deficiencies will be corrected. The purpose of the PSA is to correct new construction deficiencies found during the shakedown period; to correct contractor and government responsible deficiencies previously authorized; and accomplishment of other improvements or class items as authorized. Funding is used for corrections authorized by the ship's Program Manager as a result of builders' trials (pre-delivery), acceptance or underway trials, final contract trials, trial board items, and correction of production-related defects or deficiencies which develop during the post delivery period. Although the majority of post delivery funding occurs after ships' delivery dates, some funding is required prior to the delivery date in preparation for post delivery events. First Destination Transportation (FDT). FDT delivers material from a procurement source to the first point of use or storage which may be in the Continental United States or overseas. The procurement source may be a supplier outside of the Department of Defense (DoD) supply system or a DoD activity which fabricates new material. FDT also includes transportation from point of origin to point of use or storage when Navy-owned material or equipment is provided to a contractor incident to a Research and Development project or a system/equipment acquisition or modification.
A64: SCN | B64: Procurement | C64: 5110 | D64: Outfitting - LPD-17 | E64: 1 | F64: GFE / combat systems for newbuild | L64: 33000 | V64: [SUB] | W64: 5110 / Outfitting | X64: USN | Y64: Combatant Ships | Z64: Amphibious Warfare Ships | AA64: LPD | AB64: P-40 > LI 5110 > P-29/P-30 > LPD | AC64: 395 | AF64: 5110 | AI64: Maritime Sustainment & Lifecycle Support | AJ64: Depot-Level Repair Parts | AK64: Outfitting (OF) funds are used to acquire on board repair parts, other secondary items, equipage, recreation items, precommissioning crew support and general use consumables furnished to the shipbuilder or the fitting-out activity to fill the ship's initial allowances as defined by the baseline coordinated shipboard allowance list (COSAL). The program also budgets for contractor-furnished spares, a lead-time away from delivery. The program ensures operational readiness of ships undergoing new construction, conversion, service life extension program (SLEP), and nuclear refueling. It ensures these ships receive their full allowances of spare parts and equipment which are vitally required to support the shipboard maintenance process; ensures ships are equipped with operating space items (tools, test equipment, damage control), personnel safety and survivability commodities for successful completion of builder sea trials; supports shipboard maintenance and thereby achieving the OPNAV-directed supply readiness goals for material on board ship at delivery. SCN funding for the initial fill of allowance list items are limited to those items on the COSAL and authorized requirements through the Obligation Work Limiting Date (OWLD). While most outfitting funds are executed prior to ships' completion of fitting out dates, some outfitting funding may be required in the fiscal year following the scheduled Delivery Date. Post Delivery (PD) funding covers the repair of government-responsible items which were believed to have been complete to standard and/or operable at delivery, as well as funding to conduct tests and trials after delivery. It is essential to deliver to the Fleet complete ships, free from both contractor and government responsible deficiencies, capable of supporting the Navy's mission. The Post Shakedown Availability (PSA) is a shipyard availability assigned to commence after delivery and to be completed prior to the expiration of the SCN OWLD. It is during this time that acceptance and final contract trials deficiencies will be corrected. The purpose of the PSA is to correct new construction deficiencies found during the shakedown period; to correct contractor and government responsible deficiencies previously authorized; and accomplishment of other improvements or class items as authorized. Funding is used for corrections authorized by the ship's Program Manager as a result of builders' trials (pre-delivery), acceptance or underway trials, final contract trials, trial board items, and correction of production-related defects or deficiencies which develop during the post delivery period. Although the majority of post delivery funding occurs after ships' delivery dates, some funding is required prior to the delivery date in preparation for post delivery events. First Destination Transportation (FDT). FDT delivers material from a procurement source to the first point of use or storage which may be in the Continental United States or overseas. The procurement source may be a supplier outside of the Department of Defense (DoD) supply system or a DoD activity which fabricates new material. FDT also includes transportation from point of origin to point of use or storage when Navy-owned material or equipment is provided to a contractor incident to a Research and Development project or a system/equipment acquisition or modification.
A65: SCN | B65: Procurement | C65: 5110 | D65: Outfitting - ESB | E65: 1 | F65: GFE / combat systems for newbuild | L65: 11858 | V65: [SUB] | W65: 5110 / Outfitting | X65: MSC | Y65: Combatant Ships | Z65: Expeditionary & Seabasing Ships | AA65: T-ESB | AB65: P-40 > LI 5110 > P-29/P-30 > ESB | AC65: 395 | AF65: 5110 | AI65: Maritime Sustainment & Lifecycle Support | AJ65: Depot-Level Repair Parts | AK65: Outfitting (OF) funds are used to acquire on board repair parts, other secondary items, equipage, recreation items, precommissioning crew support and general use consumables furnished to the shipbuilder or the fitting-out activity to fill the ship's initial allowances as defined by the baseline coordinated shipboard allowance list (COSAL). The program also budgets for contractor-furnished spares, a lead-time away from delivery. The program ensures operational readiness of ships undergoing new construction, conversion, service life extension program (SLEP), and nuclear refueling. It ensures these ships receive their full allowances of spare parts and equipment which are vitally required to support the shipboard maintenance process; ensures ships are equipped with operating space items (tools, test equipment, damage control), personnel safety and survivability commodities for successful completion of builder sea trials; supports shipboard maintenance and thereby achieving the OPNAV-directed supply readiness goals for material on board ship at delivery. SCN funding for the initial fill of allowance list items are limited to those items on the COSAL and authorized requirements through the Obligation Work Limiting Date (OWLD). While most outfitting funds are executed prior to ships' completion of fitting out dates, some outfitting funding may be required in the fiscal year following the scheduled Delivery Date. Post Delivery (PD) funding covers the repair of government-responsible items which were believed to have been complete to standard and/or operable at delivery, as well as funding to conduct tests and trials after delivery. It is essential to deliver to the Fleet complete ships, free from both contractor and government responsible deficiencies, capable of supporting the Navy's mission. The Post Shakedown Availability (PSA) is a shipyard availability assigned to commence after delivery and to be completed prior to the expiration of the SCN OWLD. It is during this time that acceptance and final contract trials deficiencies will be corrected. The purpose of the PSA is to correct new construction deficiencies found during the shakedown period; to correct contractor and government responsible deficiencies previously authorized; and accomplishment of other improvements or class items as authorized. Funding is used for corrections authorized by the ship's Program Manager as a result of builders' trials (pre-delivery), acceptance or underway trials, final contract trials, trial board items, and correction of production-related defects or deficiencies which develop during the post delivery period. Although the majority of post delivery funding occurs after ships' delivery dates, some funding is required prior to the delivery date in preparation for post delivery events. First Destination Transportation (FDT). FDT delivers material from a procurement source to the first point of use or storage which may be in the Continental United States or overseas. The procurement source may be a supplier outside of the Department of Defense (DoD) supply system or a DoD activity which fabricates new material. FDT also includes transportation from point of origin to point of use or storage when Navy-owned material or equipment is provided to a contractor incident to a Research and Development project or a system/equipment acquisition or modification.
A66: SCN | B66: Procurement | C66: 5110 | D66: Outfitting - LHA | E66: 1 | F66: GFE / combat systems for newbuild | L66: 23119 | V66: [SUB] | W66: 5110 / Outfitting | X66: USN | Y66: Combatant Ships | Z66: Amphibious Warfare Ships | AA66: LHA | AB66: P-40 > LI 5110 > P-29/P-30 > LHA | AC66: 395 | AF66: 5110 | AI66: Maritime Sustainment & Lifecycle Support | AJ66: Depot-Level Repair Parts | AK66: Outfitting (OF) funds are used to acquire on board repair parts, other secondary items, equipage, recreation items, precommissioning crew support and general use consumables furnished to the shipbuilder or the fitting-out activity to fill the ship's initial allowances as defined by the baseline coordinated shipboard allowance list (COSAL). The program also budgets for contractor-furnished spares, a lead-time away from delivery. The program ensures operational readiness of ships undergoing new construction, conversion, service life extension program (SLEP), and nuclear refueling. It ensures these ships receive their full allowances of spare parts and equipment which are vitally required to support the shipboard maintenance process; ensures ships are equipped with operating space items (tools, test equipment, damage control), personnel safety and survivability commodities for successful completion of builder sea trials; supports shipboard maintenance and thereby achieving the OPNAV-directed supply readiness goals for material on board ship at delivery. SCN funding for the initial fill of allowance list items are limited to those items on the COSAL and authorized requirements through the Obligation Work Limiting Date (OWLD). While most outfitting funds are executed prior to ships' completion of fitting out dates, some outfitting funding may be required in the fiscal year following the scheduled Delivery Date. Post Delivery (PD) funding covers the repair of government-responsible items which were believed to have been complete to standard and/or operable at delivery, as well as funding to conduct tests and trials after delivery. It is essential to deliver to the Fleet complete ships, free from both contractor and government responsible deficiencies, capable of supporting the Navy's mission. The Post Shakedown Availability (PSA) is a shipyard availability assigned to commence after delivery and to be completed prior to the expiration of the SCN OWLD. It is during this time that acceptance and final contract trials deficiencies will be corrected. The purpose of the PSA is to correct new construction deficiencies found during the shakedown period; to correct contractor and government responsible deficiencies previously authorized; and accomplishment of other improvements or class items as authorized. Funding is used for corrections authorized by the ship's Program Manager as a result of builders' trials (pre-delivery), acceptance or underway trials, final contract trials, trial board items, and correction of production-related defects or deficiencies which develop during the post delivery period. Although the majority of post delivery funding occurs after ships' delivery dates, some funding is required prior to the delivery date in preparation for post delivery events. First Destination Transportation (FDT). FDT delivers material from a procurement source to the first point of use or storage which may be in the Continental United States or overseas. The procurement source may be a supplier outside of the Department of Defense (DoD) supply system or a DoD activity which fabricates new material. FDT also includes transportation from point of origin to point of use or storage when Navy-owned material or equipment is provided to a contractor incident to a Research and Development project or a system/equipment acquisition or modification.
A67: SCN | B67: Procurement | C67: 5110 | D67: Outfitting - EPF | E67: 1 | F67: GFE / combat systems for newbuild | L67: 8554 | V67: [SUB] | W67: 5110 / Outfitting | X67: MSC | Y67: Combatant Ships | Z67: Expeditionary & Seabasing Ships | AA67: T-EPF | AB67: P-40 > LI 5110 > P-29/P-30 > EPF | AC67: 395 | AF67: 5110 | AI67: Maritime Sustainment & Lifecycle Support | AJ67: Depot-Level Repair Parts | AK67: Outfitting (OF) funds are used to acquire on board repair parts, other secondary items, equipage, recreation items, precommissioning crew support and general use consumables furnished to the shipbuilder or the fitting-out activity to fill the ship's initial allowances as defined by the baseline coordinated shipboard allowance list (COSAL). The program also budgets for contractor-furnished spares, a lead-time away from delivery. The program ensures operational readiness of ships undergoing new construction, conversion, service life extension program (SLEP), and nuclear refueling. It ensures these ships receive their full allowances of spare parts and equipment which are vitally required to support the shipboard maintenance process; ensures ships are equipped with operating space items (tools, test equipment, damage control), personnel safety and survivability commodities for successful completion of builder sea trials; supports shipboard maintenance and thereby achieving the OPNAV-directed supply readiness goals for material on board ship at delivery. SCN funding for the initial fill of allowance list items are limited to those items on the COSAL and authorized requirements through the Obligation Work Limiting Date (OWLD). While most outfitting funds are executed prior to ships' completion of fitting out dates, some outfitting funding may be required in the fiscal year following the scheduled Delivery Date. Post Delivery (PD) funding covers the repair of government-responsible items which were believed to have been complete to standard and/or operable at delivery, as well as funding to conduct tests and trials after delivery. It is essential to deliver to the Fleet complete ships, free from both contractor and government responsible deficiencies, capable of supporting the Navy's mission. The Post Shakedown Availability (PSA) is a shipyard availability assigned to commence after delivery and to be completed prior to the expiration of the SCN OWLD. It is during this time that acceptance and final contract trials deficiencies will be corrected. The purpose of the PSA is to correct new construction deficiencies found during the shakedown period; to correct contractor and government responsible deficiencies previously authorized; and accomplishment of other improvements or class items as authorized. Funding is used for corrections authorized by the ship's Program Manager as a result of builders' trials (pre-delivery), acceptance or underway trials, final contract trials, trial board items, and correction of production-related defects or deficiencies which develop during the post delivery period. Although the majority of post delivery funding occurs after ships' delivery dates, some funding is required prior to the delivery date in preparation for post delivery events. First Destination Transportation (FDT). FDT delivers material from a procurement source to the first point of use or storage which may be in the Continental United States or overseas. The procurement source may be a supplier outside of the Department of Defense (DoD) supply system or a DoD activity which fabricates new material. FDT also includes transportation from point of origin to point of use or storage when Navy-owned material or equipment is provided to a contractor incident to a Research and Development project or a system/equipment acquisition or modification.
... A71: SCN | B71: Procurement | C71: 5110 | D71: Outfitting - LCU | E71: 1 | F71: GFE / combat systems for newbuild | L71: 9654 | V71: [SUB] | W71: 5110 / Outfitting | X71: USN | Y71: Combatant Crafts | Z71: Amphibious Warfare Craft | AA71: LCU | AB71: P-40 > LI 5110 > P-29/P-30 > LCU | AC71: 395 | AF71: 5110 | AI71: Maritime Sustainment & Lifecycle Support | AJ71: Depot-Level Repair Parts | AK71: Outfitting (OF) funds are used to acquire on board repair parts, other secondary items, equipage, recreation items, precommissioning crew support and general use consumables furnished to the shipbuilder or the fitting-out activity to fill the ship's initial allowances as defined by the baseline coordinated shipboard allowance list (COSAL). The program also budgets for contractor-furnished spares, a lead-time away from delivery. The program ensures operational readiness of ships undergoing new construction, conversion, service life extension program (SLEP), and nuclear refueling. It ensures these ships receive their full allowances of spare parts and equipment which are vitally required to support the shipboard maintenance process; ensures ships are equipped with operating space items (tools, test equipment, damage control), personnel safety and survivability commodities for successful completion of builder sea trials; supports shipboard maintenance and thereby achieving the OPNAV-directed supply readiness goals for material on board ship at delivery. SCN funding for the initial fill of allowance list items are limited to those items on the COSAL and authorized requirements through the Obligation Work Limiting Date (OWLD). While most outfitting funds are executed prior to ships' completion of fitting out dates, some outfitting funding may be required in the fiscal year following the scheduled Delivery Date. Post Delivery (PD) funding covers the repair of government-responsible items which were believed to have been complete to standard and/or operable at delivery, as well as funding to conduct tests and trials after delivery. It is essential to deliver to the Fleet complete ships, free from both contractor and government responsible deficiencies, capable of supporting the Navy's mission. The Post Shakedown Availability (PSA) is a shipyard availability assigned to commence after delivery and to be completed prior to the expiration of the SCN OWLD. It is during this time that acceptance and final contract trials deficiencies will be corrected. The purpose of the PSA is to correct new construction deficiencies found during the shakedown period; to correct contractor and government responsible deficiencies previously authorized; and accomplishment of other improvements or class items as authorized. Funding is used for corrections authorized by the ship's Program Manager as a result of builders' trials (pre-delivery), acceptance or underway trials, final contract trials, trial board items, and correction of production-related defects or deficiencies which develop during the post delivery period. Although the majority of post delivery funding occurs after ships' delivery dates, some funding is required prior to the delivery date in preparation for post delivery events. First Destination Transportation (FDT). FDT delivers material from a procurement source to the first point of use or storage which may be in the Continental United States or overseas. The procurement source may be a supplier outside of the Department of Defense (DoD) supply system or a DoD activity which fabricates new material. FDT also includes transportation from point of origin to point of use or storage when Navy-owned material or equipment is provided to a contractor incident to a Research and Development project or a system/equipment acquisition or modification.
A72: SCN | B72: Procurement | C72: 5110 | D72: Outfitting - SSC (Ship to Shore Connector) | E72: 1 | F72: GFE / combat systems for newbuild | L72: 17536 | P72: 239095 | Q72: 320000 | R72: 559095 | V72: [SUB] | W72: 5110 / Outfitting | X72: USN | Y72: Combatant Crafts | Z72: Amphibious Warfare Craft | AA72: LCAC | AB72: P-40 > LI 5110 > P-29/P-30 > LCAC SSC | AC72: 395 | AF72: 5110 | AI72: Maritime Sustainment & Lifecycle Support | AJ72: Depot-Level Repair Parts | AK72: Outfitting (OF) funds are used to acquire on board repair parts, other secondary items, equipage, recreation items, precommissioning crew support and general use consumables furnished to the shipbuilder or the fitting-out activity to fill the ship's initial allowances as defined by the baseline coordinated shipboard allowance list (COSAL). The program also budgets for contractor-furnished spares, a lead-time away from delivery. The program ensures operational readiness of ships undergoing new construction, conversion, service life extension program (SLEP), and nuclear refueling. It ensures these ships receive their full allowances of spare parts and equipment which are vitally required to support the shipboard maintenance process; ensures ships are equipped with operating space items (tools, test equipment, damage control), personnel safety and survivability commodities for successful completion of builder sea trials; supports shipboard maintenance and thereby achieving the OPNAV-directed supply readiness goals for material on board ship at delivery. SCN funding for the initial fill of allowance list items are limited to those items on the COSAL and authorized requirements through the Obligation Work Limiting Date (OWLD). While most outfitting funds are executed prior to ships' completion of fitting out dates, some outfitting funding may be required in the fiscal year following the scheduled Delivery Date. Post Delivery (PD) funding covers the repair of government-responsible items which were believed to have been complete to standard and/or operable at delivery, as well as funding to conduct tests and trials after delivery. It is essential to deliver to the Fleet complete ships, free from both contractor and government responsible deficiencies, capable of supporting the Navy's mission. The Post Shakedown Availability (PSA) is a shipyard availability assigned to commence after delivery and to be completed prior to the expiration of the SCN OWLD. It is during this time that acceptance and final contract trials deficiencies will be corrected. The purpose of the PSA is to correct new construction deficiencies found during the shakedown period; to correct contractor and government responsible deficiencies previously authorized; and accomplishment of other improvements or class items as authorized. Funding is used for corrections authorized by the ship's Program Manager as a result of builders' trials (pre-delivery), acceptance or underway trials, final contract trials, trial board items, and correction of production-related defects or deficiencies which develop during the post delivery period. Although the majority of post delivery funding occurs after ships' delivery dates, some funding is required prior to the delivery date in preparation for post delivery events. First Destination Transportation (FDT). FDT delivers material from a procurement source to the first point of use or storage which may be in the Continental United States or overseas. The procurement source may be a supplier outside of the Department of Defense (DoD) supply system or a DoD activity which fabricates new material. FDT also includes transportation from point of origin to point of use or storage when Navy-owned material or equipment is provided to a contractor incident to a Research and Development project or a system/equipment acquisition or modification.
A73: SCN | B73: Procurement | C73: 5110 | D73: Outfitting - LCAC SLEP | E73: 5 | F73: SLEP | L73: 493 | P73: 37390 | Q73: 0 | R73: 37390 | V73: [SUB] | W73: 5110 / Outfitting | X73: USN | Y73: Combatant Crafts | Z73: Amphibious Warfare Craft | AA73: LCAC | AB73: P-40 > LI 5110 > P-29/P-30 > LCAC SLEP | AC73: 395 | AF73: 5110 | AI73: Maritime Sustainment & Lifecycle Support | AJ73: Depot-Level Repair Parts | AK73: Outfitting (OF) funds are used to acquire on board repair parts, other secondary items, equipage, recreation items, precommissioning crew support and general use consumables furnished to the shipbuilder or the fitting-out activity to fill the ship's initial allowances as defined by the baseline coordinated shipboard allowance list (COSAL). The program also budgets for contractor-furnished spares, a lead-time away from delivery. The program ensures operational readiness of ships undergoing new construction, conversion, service life extension program (SLEP), and nuclear refueling. It ensures these ships receive their full allowances of spare parts and equipment which are vitally required to support the shipboard maintenance process; ensures ships are equipped with operating space items (tools, test equipment, damage control), personnel safety and survivability commodities for successful completion of builder sea trials; supports shipboard maintenance and thereby achieving the OPNAV-directed supply readiness goals for material on board ship at delivery. SCN funding for the initial fill of allowance list items are limited to those items on the COSAL and authorized requirements through the Obligation Work Limiting Date (OWLD). While most outfitting funds are executed prior to ships' completion of fitting out dates, some outfitting funding may be required in the fiscal year following the scheduled Delivery Date. Post Delivery (PD) funding covers the repair of government-responsible items which were believed to have been complete to standard and/or operable at delivery, as well as funding to conduct tests and trials after delivery. It is essential to deliver to the Fleet complete ships, free from both contractor and government responsible deficiencies, capable of supporting the Navy's mission. The Post Shakedown Availability (PSA) is a shipyard availability assigned to commence after delivery and to be completed prior to the expiration of the SCN OWLD. It is during this time that acceptance and final contract trials deficiencies will be corrected. The purpose of the PSA is to correct new construction deficiencies found during the shakedown period; to correct contractor and government responsible deficiencies previously authorized; and accomplishment of other improvements or class items as authorized. Funding is used for corrections authorized by the ship's Program Manager as a result of builders' trials (pre-delivery), acceptance or underway trials, final contract trials, trial board items, and correction of production-related defects or deficiencies which develop during the post delivery period. Although the majority of post delivery funding occurs after ships' delivery dates, some funding is required prior to the delivery date in preparation for post delivery events. First Destination Transportation (FDT). FDT delivers material from a procurement source to the first point of use or storage which may be in the Continental United States or overseas. The procurement source may be a supplier outside of the Department of Defense (DoD) supply system or a DoD activity which fabricates new material. FDT also includes transportation from point of origin to point of use or storage when Navy-owned material or equipment is provided to a contractor incident to a Research and Development project or a system/equipment acquisition or modification.
A74: SCN | B74: Procurement | C74: 5110 | D74: Outfitting - PUBS / First Destination | E74: 1 | F74: GFE / combat systems for newbuild | L74: 16657 | V74: [SUB] | W74: 5110 / Outfitting | AB74: P-40 > LI 5110 > P-29/P-30 > PUBS + FD | AC74: 395 | AF74: 5110 | AI74: Maritime Sustainment & Lifecycle Support | AJ74: Depot-Level Repair Parts | AK74: Outfitting (OF) funds are used to acquire on board repair parts, other secondary items, equipage, recreation items, precommissioning crew support and general use consumables furnished to the shipbuilder or the fitting-out activity to fill the ship's initial allowances as defined by the baseline coordinated shipboard allowance list (COSAL). The program also budgets for contractor-furnished spares, a lead-time away from delivery. The program ensures operational readiness of ships undergoing new construction, conversion, service life extension program (SLEP), and nuclear refueling. It ensures these ships receive their full allowances of spare parts and equipment which are vitally required to support the shipboard maintenance process; ensures ships are equipped with operating space items (tools, test equipment, damage control), personnel safety and survivability commodities for successful completion of builder sea trials; supports shipboard maintenance and thereby achieving the OPNAV-directed supply readiness goals for material on board ship at delivery. SCN funding for the initial fill of allowance list items are limited to those items on the COSAL and authorized requirements through the Obligation Work Limiting Date (OWLD). While most outfitting funds are executed prior to ships' completion of fitting out dates, some outfitting funding may be required in the fiscal year following the scheduled Delivery Date. Post Delivery (PD) funding covers the repair of government-responsible items which were believed to have been complete to standard and/or operable at delivery, as well as funding to conduct tests and trials after delivery. It is essential to deliver to the Fleet complete ships, free from both contractor and government responsible deficiencies, capable of supporting the Navy's mission. The Post Shakedown Availability (PSA) is a shipyard availability assigned to commence after delivery and to be completed prior to the expiration of the SCN OWLD. It is during this time that acceptance and final contract trials deficiencies will be corrected. The purpose of the PSA is to correct new construction deficiencies found during the shakedown period; to correct contractor and government responsible deficiencies previously authorized; and accomplishment of other improvements or class items as authorized. Funding is used for corrections authorized by the ship's Program Manager as a result of builders' trials (pre-delivery), acceptance or underway trials, final contract trials, trial board items, and correction of production-related defects or deficiencies which develop during the post delivery period. Although the majority of post delivery funding occurs after ships' delivery dates, some funding is required prior to the delivery date in preparation for post delivery events. First Destination Transportation (FDT). FDT delivers material from a procurement source to the first point of use or storage which may be in the Continental United States or overseas. The procurement source may be a supplier outside of the Department of Defense (DoD) supply system or a DoD activity which fabricates new material. FDT also includes transportation from point of origin to point of use or storage when Navy-owned material or equipment is provided to a contractor incident to a Research and Development project or a system/equipment acquisition or modification.
